Workbook

Sheet Start here
A1: Debt Payoff & Compound Interest Planner
A2: Find the fastest way out of debt, then let compounding work for you.
A4: 1. Open '1 Your debts' and replace the blue example debts with yours (up to 8). Choose Avalanche or Snowball and type your extra monthly payment.
A5: 2. Open '2 Payoff plan': your debt-free month, total interest, and how much interest and time the plan saves against paying only minimums.
A6: 3. '3 Compound growth' shows what a lump sum and a monthly amount become once the debt is gone.
A7: 4. '4 Pay debt or invest' compares what paying a debt saves (its interest rate) with an assumed investment return.
A8: 5. 'Engine (math)' is every month of the calculation in plain formulas, so you can check any number.
A10: Colors
A11: Blue = you type here
A12: Gray = formula
A14: How the plans differ
A15: Avalanche: extra money goes to the highest interest rate first. It costs the least interest.
... A22: License: personal use for you and your household. Please do not resell or redistribute the file.

Sheet 1 Your debts
A1: 1 Your debts
A2: List up to eight. Leave unused rows blank. Example debts shown.
A3: Debt | B3: Balance | C3: Yearly interest rate | D3: Monthly minimum | E3: Plan order | F3: Check | H3: priority score (helper)
A4: Credit card A (example) | B4: 4200 | C4: 0.2499 | D4: 105 | E4: =IF(H4="","",COUNTIF($H$4:$H$11,">"&H4)+1) -> 1 | F4: =IF(AND(N(B4)>0,N(D4)<N(B4)*N(C4)/12),"Minimum is below the monthly interest",IF(AND(N(B4)>0,N(D4)=0),"Enter a minimum","")) | H4: =IF(N(B4)>0,IF($B$15="Snowball",-B4*1000+(100-ROW())*0.001,N(C4)*100000000+(100-ROW())),"") -> 24990096
A5: Credit card B (example) | B5: 1800 | C5: 0.1999 | D5: 45 | E5: =IF(H5="","",COUNTIF($H$4:$H$11,">"&H5)+1) -> 2 | F5: =IF(AND(N(B5)>0,N(D5)<N(B5)*N(C5)/12),"Minimum is below the monthly interest",IF(AND(N(B5)>0,N(D5)=0),"Enter a minimum","")) | H5: =IF(N(B5)>0,IF($B$15="Snowball",-B5*1000+(100-ROW())*0.001,N(C5)*100000000+(100-ROW())),"") -> 19990095
A6: Car loan (example) | B6: 7500 | C6: 0.079 | D6: 210 | E6: =IF(H6="","",COUNTIF($H$4:$H$11,">"&H6)+1) -> 3 | F6: =IF(AND(N(B6)>0,N(D6)<N(B6)*N(C6)/12),"Minimum is below the monthly interest",IF(AND(N(B6)>0,N(D6)=0),"Enter a minimum","")) | H6: =IF(N(B6)>0,IF($B$15="Snowball",-B6*1000+(100-ROW())*0.001,N(C6)*100000000+(100-ROW())),"") -> 7900094
A7: Student loan (example) | B7: 12000 | C7: 0.055 | D7: 130 | E7: =IF(H7="","",COUNTIF($H$4:$H$11,">"&H7)+1) -> 4 | F7: =IF(AND(N(B7)>0,N(D7)<N(B7)*N(C7)/12),"Minimum is below the monthly interest",IF(AND(N(B7)>0,N(D7)=0),"Enter a minimum","")) | H7: =IF(N(B7)>0,IF($B$15="Snowball",-B7*1000+(100-ROW())*0.001,N(C7)*100000000+(100-ROW())),"") -> 5500093
E8: =IF(H8="","",COUNTIF($H$4:$H$11,">"&H8)+1) | F8: =IF(AND(N(B8)>0,N(D8)<N(B8)*N(C8)/12),"Minimum is below the monthly interest",IF(AND(N(B8)>0,N(D8)=0),"Enter a minimum","")) | H8: =IF(N(B8)>0,IF($B$15="Snowball",-B8*1000+(100-ROW())*0.001,N(C8)*100000000+(100-ROW())),"")
E9: =IF(H9="","",COUNTIF($H$4:$H$11,">"&H9)+1) | F9: =IF(AND(N(B9)>0,N(D9)<N(B9)*N(C9)/12),"Minimum is below the monthly interest",IF(AND(N(B9)>0,N(D9)=0),"Enter a minimum","")) | H9: =IF(N(B9)>0,IF($B$15="Snowball",-B9*1000+(100-ROW())*0.001,N(C9)*100000000+(100-ROW())),"")
E10: =IF(H10="","",COUNTIF($H$4:$H$11,">"&H10)+1) | F10: =IF(AND(N(B10)>0,N(D10)<N(B10)*N(C10)/12),"Minimum is below the monthly interest",IF(AND(N(B10)>0,N(D10)=0),"Enter a minimum","")) | H10: =IF(N(B10)>0,IF($B$15="Snowball",-B10*1000+(100-ROW())*0.001,N(C10)*100000000+(100-ROW())),"")
E11: =IF(H11="","",COUNTIF($H$4:$H$11,">"&H11)+1) | F11: =IF(AND(N(B11)>0,N(D11)<N(B11)*N(C11)/12),"Minimum is below the monthly interest",IF(AND(N(B11)>0,N(D11)=0),"Enter a minimum","")) | H11: =IF(N(B11)>0,IF($B$15="Snowball",-B11*1000+(100-ROW())*0.001,N(C11)*100000000+(100-ROW())),"")
A13: Plan settings
A14: Extra you can pay each month (on top of minimums) | B14: 200
A15: Method | B15: Avalanche
A16: Total you pay toward debt each month | B16: =SUMIF(B4:B11,">0",D4:D11)+N(B14) -> 690
A17: Total debt today | B17: =SUM(B4:B11) -> 25500

Sheet 2 Payoff plan
A1: 2 Payoff plan
A2: What the plan saves against paying only the minimums.
A3: Result | B3: Value
A4: Method | B4: ='1 Your debts'!B15 -> Avalanche
A5: Months to debt-free (your plan) | B5: =IF('1 Your debts'!B17<=0,0,IF(COUNTIF('Engine (math)'!$C$9:$C$248,">0.005")>=240,">240",COUNTIF('Engine (math)'!$C$9:$C$248,">0.005")+1)) -> 43
A6: Interest you will pay (your plan) | B6: =SUM('Engine (math)'!$D$9:$D$248) -> 4002.2576
A7: Months to debt-free (minimums only) | B7: =IF('1 Your debts'!B17<=0,0,IF(COUNTIF('Engine (math)'!$F$9:$F$248,">0.005")>=240,">240",COUNTIF('Engine (math)'!$F$9:$F$248,">0.005")+1)) -> 121
A8: Interest you will pay (minimums only) | B8: =SUM('Engine (math)'!$G$9:$G$248) -> 10822.835
A9: Interest saved | B9: =B8-B6 -> 6820.5771
A10: Months saved | B10: =IF(AND(ISNUMBER(B7),ISNUMBER(B5)),B7-B5,"-") -> 78
A11: Years to debt-free (your plan) | B11: =IF(ISNUMBER(B5),B5/12,"-") -> 3.5833333
A13: Minimums-only figures cover the first 20 years (240 months); a debt that would take longer shows '>240'.
A15: Paid off in this order | B15: Debt | C15: Balance | D15: Rate | E15: Paid off in month
A16: 1 | B16: ='Engine (math)'!J3 -> Credit card A (example) | C16: ='Engine (math)'!J4 -> 4200 | D16: ='Engine (math)'!J5 -> 0.2499 | E16: =IF(C16>0,IF(COUNTIF('Engine (math)'!$O$9:$O$248,">0.005")>=240,">240",COUNTIF('Engine (math)'!$O$9:$O$248,">0.005")+1),"") -> 17
A17: 2 | B17: ='Engine (math)'!T3 -> Credit card B (example) | C17: ='Engine (math)'!T4 -> 1800 | D17: ='Engine (math)'!T5 -> 0.1999 | E17: =IF(C17>0,IF(COUNTIF('Engine (math)'!$Y$9:$Y$248,">0.005")>=240,">240",COUNTIF('Engine (math)'!$Y$9:$Y$248,">0.005")+1),"") -> 21
A18: 3 | B18: ='Engine (math)'!AD3 -> Car loan (example) | C18: ='Engine (math)'!AD4 -> 7500 | D18: ='Engine (math)'!AD5 -> 0.079 | E18: =IF(C18>0,IF(COUNTIF('Engine (math)'!$AI$9:$AI$248,">0.005")>=240,">240",COUNTIF('Engine (math)'!$AI$9:$AI$248,">0.005")+1),"") -> 29
A19: 4 | B19: ='Engine (math)'!AN3 -> Student loan (example) | C19: ='Engine (math)'!AN4 -> 12000 | D19: ='Engine (math)'!AN5 -> 0.055 | E19: =IF(C19>0,IF(COUNTIF('Engine (math)'!$AS$9:$AS$248,">0.005")>=240,">240",COUNTIF('Engine (math)'!$AS$9:$AS$248,">0.005")+1),"") -> 43
A20: 5 | B20: ='Engine (math)'!AX3 | C20: ='Engine (math)'!AX4 -> 0 | D20: ='Engine (math)'!AX5 -> 0 | E20: =IF(C20>0,IF(COUNTIF('Engine (math)'!$BC$9:$BC$248,">0.005")>=240,">240",COUNTIF('Engine (math)'!$BC$9:$BC$248,">0.005")+1),"")
A21: 6 | B21: ='Engine (math)'!BH3 | C21: ='Engine (math)'!BH4 -> 0 | D21: ='Engine (math)'!BH5 -> 0 | E21: =IF(C21>0,IF(COUNTIF('Engine (math)'!$BM$9:$BM$248,">0.005")>=240,">240",COUNTIF('Engine (math)'!$BM$9:$BM$248,">0.005")+1),"")
A22: 7 | B22: ='Engine (math)'!BR3 | C22: ='Engine (math)'!BR4 -> 0 | D22: ='Engine (math)'!BR5 -> 0 | E22: =IF(C22>0,IF(COUNTIF('Engine (math)'!$BW$9:$BW$248,">0.005")>=240,">240",COUNTIF('Engine (math)'!$BW$9:$BW$248,">0.005")+1),"")
A23: 8 | B23: ='Engine (math)'!CB3 | C23: ='Engine (math)'!CB4 -> 0 | D23: ='Engine (math)'!CB5 -> 0 | E23: =IF(C23>0,IF(COUNTIF('Engine (math)'!$CG$9:$CG$248,">0.005")>=240,">240",COUNTIF('Engine (math)'!$CG$9:$CG$248,">0.005")+1),"")

Sheet 3 Compound growth
A1: 3 Compound growth
A2: What a starting amount plus a monthly amount become. Returns are assumptions, never promises.
A4: Starting amount | B4: 5000
A5: Monthly amount you add | B5: 300
A6: Expected yearly return (assumption) | B6: 0.07
A7: Years | B7: 30
A9: Value at the end of your years | B9: =FV(B6/12,B7*12,-B5,-B4) -> 406573.79
A10: Of which you put in | B10: =B4+B5*B7*12 -> 113000
A11: Growth you did not have to earn | B11: =B9-B10 -> 293573.79
A12: Years to double (rule of 72) | B12: =IF(B6>0,72/(B6*100),"-") -> 10.285714
A14: Year | B14: Value | C14: You put in | D14: Growth
A15: 0 | B15: =FV($B$6/12,A15*12,-$B$5,-$B$4) -> 5000 | C15: =$B$4+$B$5*A15*12 -> 5000 | D15: =B15-C15 -> 0
A16: 1 | B16: =FV($B$6/12,A16*12,-$B$5,-$B$4) -> 9079.226 | C16: =$B$4+$B$5*A16*12 -> 8600 | D16: =B16-C16 -> 479.22599
A17: 2 | B17: =FV($B$6/12,A17*12,-$B$5,-$B$4) -> 13453.34 | C17: =$B$4+$B$5*A17*12 -> 12200 | D17: =B17-C17 -> 1253.3396
A18: 3 | B18: =FV($B$6/12,A18*12,-$B$5,-$B$4) -> 18143.658 | C18: =$B$4+$B$5*A18*12 -> 15800 | D18: =B18-C18 -> 2343.6582
A19: 4 | B19: =FV($B$6/12,A19*12,-$B$5,-$B$4) -> 23173.04 | C19: =$B$4+$B$5*A19*12 -> 19400 | D19: =B19-C19 -> 3773.0403
A20: 5 | B20: =FV($B$6/12,A20*12,-$B$5,-$B$4) -> 28565.997 | C20: =$B$4+$B$5*A20*12 -> 23000 | D20: =B20-C20 -> 5565.9968
A21: 6 | B21: =FV($B$6/12,A21*12,-$B$5,-$B$4) -> 34348.811 | C21: =$B$4+$B$5*A21*12 -> 26600 | D21: =B21-C21 -> 7748.8106
A22: 7 | B22: =FV($B$6/12,A22*12,-$B$5,-$B$4) -> 40549.664 | C22: =$B$4+$B$5*A22*12 -> 30200 | D22: =B22-C22 -> 10349.664
A23: 8 | B23: =FV($B$6/12,A23*12,-$B$5,-$B$4) -> 47198.779 | C23: =$B$4+$B$5*A23*12 -> 33800 | D23: =B23-C23 -> 13398.779
A24: 9 | B24: =FV($B$6/12,A24*12,-$B$5,-$B$4) -> 54328.558 | C24: =$B$4+$B$5*A24*12 -> 37400 | D24: =B24-C24 -> 16928.558
A25: 10 | B25: =FV($B$6/12,A25*12,-$B$5,-$B$4) -> 61973.749 | C25: =$B$4+$B$5*A25*12 -> 41000 | D25: =B25-C25 -> 20973.749
A26: 11 | B26: =FV($B$6/12,A26*12,-$B$5,-$B$4) -> 70171.612 | C26: =$B$4+$B$5*A26*12 -> 44600 | D26: =B26-C26 -> 25571.612
... A55: 40 | B55: =FV($B$6/12,A55*12,-$B$5,-$B$4) -> 869001.08 | C55: =$B$4+$B$5*A55*12 -> 149000 | D55: =B55-C55 -> 720001.08

Sheet 4 Pay debt or invest
A1: 4 Pay debt or invest?
A2: Paying a debt saves its interest rate. Investing earns an assumed return, with risk.
A4: Interest rate of the debt (yearly) | B4: 0.2499
A5: Extra you could use each month | B5: 200
A6: Expected investment return (assumption) | B6: 0.07
A7: Years | B7: 5
A9: Value if the extra pays the debt (as long as it exists) | B9: =FV(B4/12,B7*12,-B5) -> 23472.908
A10: Value if the extra is invested | B10: =FV(B6/12,B7*12,-B5) -> 14318.58
A11: Verdict | B11: =IF(B4>B6,"Pay the debt first: its rate beats your assumed return","Investing may win on paper, but returns are not guaranteed: keep a $1,000 buffer, then compare risk") -> Pay the debt first: its rate beats your assumed return
A13: Rule of thumb: paying off a 24% debt beats almost any assumed return; a 4% loan may not. Paying a debt saves its known rate; investing earns an assumed return, with risk. Taxes, employer matches and your own situation change the answer; this is education, not advice.

Sheet Engine (math)
A1: Engine (math): every month, every debt, plain formulas. Nothing here needs editing.
J3: =IFERROR(INDEX('1 Your debts'!$A$4:$A$11,MATCH(1,'1 Your debts'!$E$4:$E$11,0)),"") -> Credit card A (example) | T3: =IFERROR(INDEX('1 Your debts'!$A$4:$A$11,MATCH(2,'1 Your debts'!$E$4:$E$11,0)),"") -> Credit card B (example) | AD3: =IFERROR(INDEX('1 Your debts'!$A$4:$A$11,MATCH(3,'1 Your debts'!$E$4:$E$11,0)),"") -> Car loan (example) | AN3: =IFERROR(INDEX('1 Your debts'!$A$4:$A$11,MATCH(4,'1 Your debts'!$E$4:$E$11,0)),"") -> Student loan (example) | AX3: =IFERROR(INDEX('1 Your debts'!$A$4:$A$11,MATCH(5,'1 Your debts'!$E$4:$E$11,0)),"") | BH3: =IFERROR(INDEX('1 Your debts'!$A$4:$A$11,MATCH(6,'1 Your debts'!$E$4:$E$11,0)),"") | BR3: =IFERROR(INDEX('1 Your debts'!$A$4:$A$11,MATCH(7,'1 Your debts'!$E$4:$E$11,0)),"") | CB3: =IFERROR(INDEX('1 Your debts'!$A$4:$A$11,MATCH(8,'1 Your debts'!$E$4:$E$11,0)),"")
J4: =IFERROR(INDEX('1 Your debts'!$B$4:$B$11,MATCH(1,'1 Your debts'!$E$4:$E$11,0)),0) -> 4200 | T4: =IFERROR(INDEX('1 Your debts'!$B$4:$B$11,MATCH(2,'1 Your debts'!$E$4:$E$11,0)),0) -> 1800 | AD4: =IFERROR(INDEX('1 Your debts'!$B$4:$B$11,MATCH(3,'1 Your debts'!$E$4:$E$11,0)),0) -> 7500 | AN4: =IFERROR(INDEX('1 Your debts'!$B$4:$B$11,MATCH(4,'1 Your debts'!$E$4:$E$11,0)),0) -> 12000 | AX4: =IFERROR(INDEX('1 Your debts'!$B$4:$B$11,MATCH(5,'1 Your debts'!$E$4:$E$11,0)),0) -> 0 | BH4: =IFERROR(INDEX('1 Your debts'!$B$4:$B$11,MATCH(6,'1 Your debts'!$E$4:$E$11,0)),0) -> 0 | BR4: =IFERROR(INDEX('1 Your debts'!$B$4:$B$11,MATCH(7,'1 Your debts'!$E$4:$E$11,0)),0) -> 0 | CB4: =IFERROR(INDEX('1 Your debts'!$B$4:$B$11,MATCH(8,'1 Your debts'!$E$4:$E$11,0)),0) -> 0
J5: =IFERROR(INDEX('1 Your debts'!$C$4:$C$11,MATCH(1,'1 Your debts'!$E$4:$E$11,0)),0) -> 0.2499 | T5: =IFERROR(INDEX('1 Your debts'!$C$4:$C$11,MATCH(2,'1 Your debts'!$E$4:$E$11,0)),0) -> 0.1999 | AD5: =IFERROR(INDEX('1 Your debts'!$C$4:$C$11,MATCH(3,'1 Your debts'!$E$4:$E$11,0)),0) -> 0.079 | AN5: =IFERROR(INDEX('1 Your debts'!$C$4:$C$11,MATCH(4,'1 Your debts'!$E$4:$E$11,0)),0) -> 0.055 | AX5: =IFERROR(INDEX('1 Your debts'!$C$4:$C$11,MATCH(5,'1 Your debts'!$E$4:$E$11,0)),0) -> 0 | BH5: =IFERROR(INDEX('1 Your debts'!$C$4:$C$11,MATCH(6,'1 Your debts'!$E$4:$E$11,0)),0) -> 0 | BR5: =IFERROR(INDEX('1 Your debts'!$C$4:$C$11,MATCH(7,'1 Your debts'!$E$4:$E$11,0)),0) -> 0 | CB5: =IFERROR(INDEX('1 Your debts'!$C$4:$C$11,MATCH(8,'1 Your debts'!$E$4:$E$11,0)),0) -> 0
J6: =IFERROR(INDEX('1 Your debts'!$D$4:$D$11,MATCH(1,'1 Your debts'!$E$4:$E$11,0)),0) -> 105 | T6: =IFERROR(INDEX('1 Your debts'!$D$4:$D$11,MATCH(2,'1 Your debts'!$E$4:$E$11,0)),0) -> 45 | AD6: =IFERROR(INDEX('1 Your debts'!$D$4:$D$11,MATCH(3,'1 Your debts'!$E$4:$E$11,0)),0) -> 210 | AN6: =IFERROR(INDEX('1 Your debts'!$D$4:$D$11,MATCH(4,'1 Your debts'!$E$4:$E$11,0)),0) -> 130 | AX6: =IFERROR(INDEX('1 Your debts'!$D$4:$D$11,MATCH(5,'1 Your debts'!$E$4:$E$11,0)),0) -> 0 | BH6: =IFERROR(INDEX('1 Your debts'!$D$4:$D$11,MATCH(6,'1 Your debts'!$E$4:$E$11,0)),0) -> 0 | BR6: =IFERROR(INDEX('1 Your debts'!$D$4:$D$11,MATCH(7,'1 Your debts'!$E$4:$E$11,0)),0) -> 0 | CB6: =IFERROR(INDEX('1 Your debts'!$D$4:$D$11,MATCH(8,'1 Your debts'!$E$4:$E$11,0)),0) -> 0
J7: Debt in plan order 1: balance, rate, minimum (rows 4-6) | T7: Debt in plan order 2: balance, rate, minimum (rows 4-6) | AD7: Debt in plan order 3: balance, rate, minimum (rows 4-6) | AN7: Debt in plan order 4: balance, rate, minimum (rows 4-6) | AX7: Debt in plan order 5: balance, rate, minimum (rows 4-6) | BH7: Debt in plan order 6: balance, rate, minimum (rows 4-6) | BR7: Debt in plan order 7: balance, rate, minimum (rows 4-6) | CB7: Debt in plan order 8: balance, rate, minimum (rows 4-6)
A8: Month | B8: Left after minimums | C8: Plan: total owed | D8: Plan: interest | F8: Min-only: total owed | G8: Min-only: interest | J8: start | K8: interest | L8: minimum | M8: extra | N8: left | O8: end | P8: min-only start | Q8: min-only interest | R8: min-only paid | S8: min-only end | T8: start | U8: interest | V8: minimum | W8: extra | X8: left | Y8: end | Z8: min-only start | AA8: min-only interest | AB8: min-only paid | AC8: min-only end | AD8: start | AE8: interest | AF8: minimum | AG8: extra | AH8: left | AI8: end | AJ8: min-only start | AK8: min-only interest | AL8: min-only paid | AM8: min-only end | AN8: start | AO8: interest | AP8: minimum | AQ8: extra | AR8: left | AS8: end | AT8: min-only start | AU8: min-only interest | AV8: min-only paid | AW8: min-only end | AX8: start | AY8: interest | AZ8: minimum | BA8: extra | BB8: left | BC8: end | BD8: min-only start | BE8: min-only interest | BF8: min-only paid | BG8: min-only end | BH8: start | BI8: interest | BJ8: minimum | BK8: extra | BL8: left | BM8: end | BN8: min-only start | BO8: min-only interest | BP8: min-only paid | BQ8: min-only end | BR8: start | BS8: interest | BT8: minimum | BU8: extra | BV8: left | BW8: end | BX8: min-only start | BY8: min-only interest | BZ8: min-only paid | CA8: min-only end | CB8: start | CC8: interest | CD8: minimum | CE8: extra | CF8: left | CG8: end | CH8: min-only start | CI8: min-only interest | CJ8: min-only paid | CK8: min-only end
A9: 1 | B9: ='1 Your debts'!$B$16-(L9+V9+AF9+AP9+AZ9+BJ9+BT9+CD9) -> 200 | C9: =O9+Y9+AI9+AS9+BC9+BM9+BW9+CG9 -> 25031.825 | D9: =K9+U9+AE9+AO9+AY9+BI9+BS9+CC9 -> 221.825 | F9: =S9+AC9+AM9+AW9+BG9+BQ9+CA9+CK9 -> 25231.825 | G9: =Q9+AA9+AK9+AU9+BE9+BO9+BY9+CI9 -> 221.825 | J9: =$J$4 -> 4200 | K9: =J9*$J$5/12 -> 87.465 | L9: =MIN($J$6,J9+K9) -> 105 | M9: =MAX(0,MIN($B9,J9+K9-L9)) -> 200 | N9: =$B9-M9 -> 0 | O9: =J9+K9-L9-M9 -> 3982.465 | P9: =$J$4 -> 4200 | Q9: =P9*$J$5/12 -> 87.465 | R9: =MIN($J$6,P9+Q9) -> 105 | S9: =P9+Q9-R9 -> 4182.465 | T9: =$T$4 -> 1800 | U9: =T9*$T$5/12 -> 29.985 | V9: =MIN($T$6,T9+U9) -> 45 | W9: =MAX(0,MIN(N9,T9+U9-V9)) -> 0 | X9: =N9-W9 -> 0 | Y9: =T9+U9-V9-W9 -> 1784.985 | Z9: =$T$4 -> 1800 | AA9: =Z9*$T$5/12 -> 29.985 | AB9: =MIN($T$6,Z9+AA9) -> 45 | AC9: =Z9+AA9-AB9 -> 1784.985 | AD9: =$AD$4 -> 7500 | AE9: =AD9*$AD$5/12 -> 49.375 | AF9: =MIN($AD$6,AD9+AE9) -> 210 | AG9: =MAX(0,MIN(X9,AD9+AE9-AF9)) -> 0 | AH9: =X9-AG9 -> 0 | AI9: =AD9+AE9-AF9-AG9 -> 7339.375 | AJ9: =$AD$4 -> 7500 | AK9: =AJ9*$AD$5/12 -> 49.375 | AL9: =MIN($AD$6,AJ9+AK9) -> 210 | AM9: =AJ9+AK9-AL9 -> 7339.375 | AN9: =$AN$4 -> 12000 | AO9: =AN9*$AN$5/12 -> 55 | AP9: =MIN($AN$6,AN9+AO9) -> 130 | AQ9: =MAX(0,MIN(AH9,AN9+AO9-AP9)) -> 0 | AR9: =AH9-AQ9 -> 0 | AS9: =AN9+AO9-AP9-AQ9 -> 11925 | AT9: =$AN$4 -> 12000 | AU9: =AT9*$AN$5/12 -> 55 | AV9: =MIN($AN$6,AT9+AU9) -> 130 | AW9: =AT9+AU9-AV9 -> 11925 | AX9: =$AX$4 -> 0 | AY9: =AX9*$AX$5/12 -> 0 | AZ9: =MIN($AX$6,AX9+AY9) -> 0 | BA9: =MAX(0,MIN(AR9,AX9+AY9-AZ9)) -> 0 | BB9: =AR9-BA9 -> 0 | BC9: =AX9+AY9-AZ9-BA9 -> 0 | BD9: =$AX$4 -> 0 | BE9: =BD9*$AX$5/12 -> 0 | BF9: =MIN($AX$6,BD9+BE9) -> 0 | BG9: =BD9+BE9-BF9 -> 0 | BH9: =$BH$4 -> 0 | BI9: =BH9*$BH$5/12 -> 0 | BJ9: =MIN($BH$6,BH9+BI9) -> 0 | BK9: =MAX(0,MIN(BB9,BH9+BI9-BJ9)) -> 0 | BL9: =BB9-BK9 -> 0 | BM9: =BH9+BI9-BJ9-BK9 -> 0 | BN9: =$BH$4 -> 0 | BO9: =BN9*$BH$5/12 -> 0 | BP9: =MIN($BH$6,BN9+BO9) -> 0 | BQ9: =BN9+BO9-BP9 -> 0 | BR9: =$BR$4 -> 0 | BS9: =BR9*$BR$5/12 -> 0 | BT9: =MIN($BR$6,BR9+BS9) -> 0 | BU9: =MAX(0,MIN(BL9,BR9+BS9-BT9)) -> 0 | BV9: =BL9-BU9 -> 0 | BW9: =BR9+BS9-BT9-BU9 -> 0 | BX9: =$BR$4 -> 0 | BY9: =BX9*$BR$5/12 -> 0 | BZ9: =MIN($BR$6,BX9+BY9) -> 0 | CA9: =BX9+BY9-BZ9 -> 0 | CB9: =$CB$4 -> 0 | CC9: =CB9*$CB$5/12 -> 0 | CD9: =MIN($CB$6,CB9+CC9) -> 0 | CE9: =MAX(0,MIN(BV9,CB9+CC9-CD9)) -> 0 | CF9: =BV9-CE9 -> 0 | CG9: =CB9+CC9-CD9-CE9 -> 0 | CH9: =$CB$4 -> 0 | CI9: =CH9*$CB$5/12 -> 0 | CJ9: =MIN($CB$6,CH9+CI9) -> 0 | CK9: =CH9+CI9-CJ9 -> 0
A10: 2 | B10: ='1 Your debts'!$B$16-(L10+V10+AF10+AP10+AZ10+BJ10+BT10+CD10) -> 200 | C10: =O10+Y10+AI10+AS10+BC10+BM10+BW10+CG10 -> 24557.469 | D10: =K10+U10+AE10+AO10+AY10+BI10+BS10+CC10 -> 215.64351 | F10: =S10+AC10+AM10+AW10+BG10+BQ10+CA10+CK10 -> 24961.634 | G10: =Q10+AA10+AK10+AU10+BE10+BO10+BY10+CI10 -> 219.80851 | J10: =O9 -> 3982.465 | K10: =J10*$J$5/12 -> 82.934834 | L10: =MIN($J$6,J10+K10) -> 105 | M10: =MAX(0,MIN($B10,J10+K10-L10)) -> 200 | N10: =$B10-M10 -> 0 | O10: =J10+K10-L10-M10 -> 3760.3998 | P10: =S9 -> 4182.465 | Q10: =P10*$J$5/12 -> 87.099834 | R10: =MIN($J$6,P10+Q10) -> 105 | S10: =P10+Q10-R10 -> 4164.5648 | T10: =Y9 -> 1784.985 | U10: =T10*$T$5/12 -> 29.734875 | V10: =MIN($T$6,T10+U10) -> 45 | W10: =MAX(0,MIN(N10,T10+U10-V10)) -> 0 | X10: =N10-W10 -> 0 | Y10: =T10+U10-V10-W10 -> 1769.7199 | Z10: =AC9 -> 1784.985 | AA10: =Z10*$T$5/12 -> 29.734875 | AB10: =MIN($T$6,Z10+AA10) -> 45 | AC10: =Z10+AA10-AB10 -> 1769.7199 | AD10: =AI9 -> 7339.375 | AE10: =AD10*$AD$5/12 -> 48.317552 | AF10: =MIN($AD$6,AD10+AE10) -> 210 | AG10: =MAX(0,MIN(X10,AD10+AE10-AF10)) -> 0 | AH10: =X10-AG10 -> 0 | AI10: =AD10+AE10-AF10-AG10 -> 7177.6926 | AJ10: =AM9 -> 7339.375 | AK10: =AJ10*$AD$5/12 -> 48.317552 | AL10: =MIN($AD$6,AJ10+AK10) -> 210 | AM10: =AJ10+AK10-AL10 -> 7177.6926 | AN10: =AS9 -> 11925 | AO10: =AN10*$AN$5/12 -> 54.65625 | AP10: =MIN($AN$6,AN10+AO10) -> 130 | AQ10: =MAX(0,MIN(AH10,AN10+AO10-AP10)) -> 0 | AR10: =AH10-AQ10 -> 0 | AS10: =AN10+AO10-AP10-AQ10 -> 11849.656 | AT10: =AW9 -> 11925 | AU10: =AT10*$AN$5/12 -> 54.65625 | AV10: =MIN($AN$6,AT10+AU10) -> 130 | AW10: =AT10+AU10-AV10 -> 11849.656 | AX10: =BC9 -> 0 | AY10: =AX10*$AX$5/12 -> 0 | AZ10: =MIN($AX$6,AX10+AY10) -> 0 | BA10: =MAX(0,MIN(AR10,AX10+AY10-AZ10)) -> 0 | BB10: =AR10-BA10 -> 0 | BC10: =AX10+AY10-AZ10-BA10 -> 0 | BD10: =BG9 -> 0 | BE10: =BD10*$AX$5/12 -> 0 | BF10: =MIN($AX$6,BD10+BE10) -> 0 | BG10: =BD10+BE10-BF10 -> 0 | BH10: =BM9 -> 0 | BI10: =BH10*$BH$5/12 -> 0 | BJ10: =MIN($BH$6,BH10+BI10) -> 0 | BK10: =MAX(0,MIN(BB10,BH10+BI10-BJ10)) -> 0 | BL10: =BB10-BK10 -> 0 | BM10: =BH10+BI10-BJ10-BK10 -> 0 | BN10: =BQ9 -> 0 | BO10: =BN10*$BH$5/12 -> 0 | BP10: =MIN($BH$6,BN10+BO10) -> 0 | BQ10: =BN10+BO10-BP10 -> 0 | BR10: =BW9 -> 0 | BS10: =BR10*$BR$5/12 -> 0 | BT10: =MIN($BR$6,BR10+BS10) -> 0 | BU10: =MAX(0,MIN(BL10,BR10+BS10-BT10)) -> 0 | BV10: =BL10-BU10 -> 0 | BW10: =BR10+BS10-BT10-BU10 -> 0 | BX10: =CA9 -> 0 | BY10: =BX10*$BR$5/12 -> 0 | BZ10: =MIN($BR$6,BX10+BY10) -> 0 | CA10: =BX10+BY10-BZ10 -> 0 | CB10: =CG9 -> 0 | CC10: =CB10*$CB$5/12 -> 0 | CD10: =MIN($CB$6,CB10+CC10) -> 0 | CE10: =MAX(0,MIN(BV10,CB10+CC10-CD10)) -> 0 | CF10: =BV10-CE10 -> 0 | CG10: =CB10+CC10-CD10-CE10 -> 0 | CH10: =CK9 -> 0 | CI10: =CH10*$CB$5/12 -> 0 | CJ10: =MIN($CB$6,CH10+CI10) -> 0 | CK10: =CH10+CI10-CJ10 -> 0
A11: 3 | B11: ='1 Your debts'!$B$16-(L11+V11+AF11+AP11+AZ11+BJ11+BT11+CD11) -> 200 | C11: =O11+Y11+AI11+AS11+BC11+BM11+BW11+CG11 -> 24076.823 | D11: =K11+U11+AE11+AO11+AY11+BI11+BS11+CC11 -> 209.35498 | F11: =S11+AC11+AM11+AW11+BG11+BQ11+CA11+CK11 -> 24689.405 | G11: =Q11+AA11+AK11+AU11+BE11+BO11+BY11+CI11 -> 217.77171 | J11: =O10 -> 3760.3998 | K11: =J11*$J$5/12 -> 78.310327 | L11: =MIN($J$6,J11+K11) -> 105 | M11: =MAX(0,MIN($B11,J11+K11-L11)) -> 200 | N11: =$B11-M11 -> 0 | O11: =J11+K11-L11-M11 -> 3533.7102 | P11: =S10 -> 4164.5648 | Q11: =P11*$J$5/12 -> 86.727063 | R11: =MIN($J$6,P11+Q11) -> 105 | S11: =P11+Q11-R11 -> 4146.2919 | T11: =Y10 -> 1769.7199 | U11: =T11*$T$5/12 -> 29.480584 | V11: =MIN($T$6,T11+U11) -> 45 | W11: =MAX(0,MIN(N11,T11+U11-V11)) -> 0 | X11: =N11-W11 -> 0 | Y11: =T11+U11-V11-W11 -> 1754.2005 | Z11: =AC10 -> 1769.7199 | AA11: =Z11*$T$5/12 -> 29.480584 | AB11: =MIN($T$6,Z11+AA11) -> 45 | AC11: =Z11+AA11-AB11 -> 1754.2005 | AD11: =AI10 -> 7177.6926 | AE11: =AD11*$AD$5/12 -> 47.253143 | AF11: =MIN($AD$6,AD11+AE11) -> 210 | AG11: =MAX(0,MIN(X11,AD11+AE11-AF11)) -> 0 | AH11: =X11-AG11 -> 0 | AI11: =AD11+AE11-AF11-AG11 -> 7014.9457 | AJ11: =AM10 -> 7177.6926 | AK11: =AJ11*$AD$5/12 -> 47.253143 | AL11: =MIN($AD$6,AJ11+AK11) -> 210 | AM11: =AJ11+AK11-AL11 -> 7014.9457 | AN11: =AS10 -> 11849.656 | AO11: =AN11*$AN$5/12 -> 54.310924 | AP11: =MIN($AN$6,AN11+AO11) -> 130 | AQ11: =MAX(0,MIN(AH11,AN11+AO11-AP11)) -> 0 | AR11: =AH11-AQ11 -> 0 | AS11: =AN11+AO11-AP11-AQ11 -> 11773.967 | AT11: =AW10 -> 11849.656 | AU11: =AT11*$AN$5/12 -> 54.310924 | AV11: =MIN($AN$6,AT11+AU11) -> 130 | AW11: =AT11+AU11-AV11 -> 11773.967 | AX11: =BC10 -> 0 | AY11: =AX11*$AX$5/12 -> 0 | AZ11: =MIN($AX$6,AX11+AY11) -> 0 | BA11: =MAX(0,MIN(AR11,AX11+AY11-AZ11)) -> 0 | BB11: =AR11-BA11 -> 0 | BC11: =AX11+AY11-AZ11-BA11 -> 0 | BD11: =BG10 -> 0 | BE11: =BD11*$AX$5/12 -> 0 | BF11: =MIN($AX$6,BD11+BE11) -> 0 | BG11: =BD11+BE11-BF11 -> 0 | BH11: =BM10 -> 0 | BI11: =BH11*$BH$5/12 -> 0 | BJ11: =MIN($BH$6,BH11+BI11) -> 0 | BK11: =MAX(0,MIN(BB11,BH11+BI11-BJ11)) -> 0 | BL11: =BB11-BK11 -> 0 | BM11: =BH11+BI11-BJ11-BK11 -> 0 | BN11: =BQ10 -> 0 | BO11: =BN11*$BH$5/12 -> 0 | BP11: =MIN($BH$6,BN11+BO11) -> 0 | BQ11: =BN11+BO11-BP11 -> 0 | BR11: =BW10 -> 0 | BS11: =BR11*$BR$5/12 -> 0 | BT11: =MIN($BR$6,BR11+BS11) -> 0 | BU11: =MAX(0,MIN(BL11,BR11+BS11-BT11)) -> 0 | BV11: =BL11-BU11 -> 0 | BW11: =BR11+BS11-BT11-BU11 -> 0 | BX11: =CA10 -> 0 | BY11: =BX11*$BR$5/12 -> 0 | BZ11: =MIN($BR$6,BX11+BY11) -> 0 | CA11: =BX11+BY11-BZ11 -> 0 | CB11: =CG10 -> 0 | CC11: =CB11*$CB$5/12 -> 0 | CD11: =MIN($CB$6,CB11+CC11) -> 0 | CE11: =MAX(0,MIN(BV11,CB11+CC11-CD11)) -> 0 | CF11: =BV11-CE11 -> 0 | CG11: =CB11+CC11-CD11-CE11 -> 0 | CH11: =CK10 -> 0 | CI11: =CH11*$CB$5/12 -> 0 | CJ11: =MIN($CB$6,CH11+CI11) -> 0 | CK11: =CH11+CI11-CJ11 -> 0
A12: 4 | B12: ='1 Your debts'!$B$16-(L12+V12+AF12+AP12+AZ12+BJ12+BT12+CD12) -> 200 | C12: =O12+Y12+AI12+AS12+BC12+BM12+BW12+CG12 -> 23589.781 | D12: =K12+U12+AE12+AO12+AY12+BI12+BS12+CC12 -> 202.95731 | F12: =S12+AC12+AM12+AW12+BG12+BQ12+CA12+CK12 -> 24415.12 | G12: =Q12+AA12+AK12+AU12+BE12+BO12+BY12+CI12 -> 215.71433 | J12: =O11 -> 3533.7102 | K12: =J12*$J$5/12 -> 73.589514 | L12: =MIN($J$6,J12+K12) -> 105 | M12: =MAX(0,MIN($B12,J12+K12-L12)) -> 200 | N12: =$B12-M12 -> 0 | O12: =J12+K12-L12-M12 -> 3302.2997 | P12: =S11 -> 4146.2919 | Q12: =P12*$J$5/12 -> 86.346529 | R12: =MIN($J$6,P12+Q12) -> 105 | S12: =P12+Q12-R12 -> 4127.6384 | T12: =Y11 -> 1754.2005 | U12: =T12*$T$5/12 -> 29.222056 | V12: =MIN($T$6,T12+U12) -> 45 | W12: =MAX(0,MIN(N12,T12+U12-V12)) -> 0 | X12: =N12-W12 -> 0 | Y12: =T12+U12-V12-W12 -> 1738.4225 | Z12: =AC11 -> 1754.2005 | AA12: =Z12*$T$5/12 -> 29.222056 | AB12: =MIN($T$6,Z12+AA12) -> 45 | AC12: =Z12+AA12-AB12 -> 1738.4225 | AD12: =AI11 -> 7014.9457 | AE12: =AD12*$AD$5/12 -> 46.181726 | AF12: =MIN($AD$6,AD12+AE12) -> 210 | AG12: =MAX(0,MIN(X12,AD12+AE12-AF12)) -> 0 | AH12: =X12-AG12 -> 0 | AI12: =AD12+AE12-AF12-AG12 -> 6851.1274 | AJ12: =AM11 -> 7014.9457 | AK12: =AJ12*$AD$5/12 -> 46.181726 | AL12: =MIN($AD$6,AJ12+AK12) -> 210 | AM12: =AJ12+AK12-AL12 -> 6851.1274 | AN12: =AS11 -> 11773.967 | AO12: =AN12*$AN$5/12 -> 53.964016 | AP12: =MIN($AN$6,AN12+AO12) -> 130 | AQ12: =MAX(0,MIN(AH12,AN12+AO12-AP12)) -> 0 | AR12: =AH12-AQ12 -> 0 | AS12: =AN12+AO12-AP12-AQ12 -> 11697.931 | AT12: =AW11 -> 11773.967 | AU12: =AT12*$AN$5/12 -> 53.964016 | AV12: =MIN($AN$6,AT12+AU12) -> 130 | AW12: =AT12+AU12-AV12 -> 11697.931 | AX12: =BC11 -> 0 | AY12: =AX12*$AX$5/12 -> 0 | AZ12: =MIN($AX$6,AX12+AY12) -> 0 | BA12: =MAX(0,MIN(AR12,AX12+AY12-AZ12)) -> 0 | BB12: =AR12-BA12 -> 0 | BC12: =AX12+AY12-AZ12-BA12 -> 0 | BD12: =BG11 -> 0 | BE12: =BD12*$AX$5/12 -> 0 | BF12: =MIN($AX$6,BD12+BE12) -> 0 | BG12: =BD12+BE12-BF12 -> 0 | BH12: =BM11 -> 0 | BI12: =BH12*$BH$5/12 -> 0 | BJ12: =MIN($BH$6,BH12+BI12) -> 0 | BK12: =MAX(0,MIN(BB12,BH12+BI12-BJ12)) -> 0 | BL12: =BB12-BK12 -> 0 | BM12: =BH12+BI12-BJ12-BK12 -> 0 | BN12: =BQ11 -> 0 | BO12: =BN12*$BH$5/12 -> 0 | BP12: =MIN($BH$6,BN12+BO12) -> 0 | BQ12: =BN12+BO12-BP12 -> 0 | BR12: =BW11 -> 0 | BS12: =BR12*$BR$5/12 -> 0 | BT12: =MIN($BR$6,BR12+BS12) -> 0 | BU12: =MAX(0,MIN(BL12,BR12+BS12-BT12)) -> 0 | BV12: =BL12-BU12 -> 0 | BW12: =BR12+BS12-BT12-BU12 -> 0 | BX12: =CA11 -> 0 | BY12: =BX12*$BR$5/12 -> 0 | BZ12: =MIN($BR$6,BX12+BY12) -> 0 | CA12: =BX12+BY12-BZ12 -> 0 | CB12: =CG11 -> 0 | CC12: =CB12*$CB$5/12 -> 0 | CD12: =MIN($CB$6,CB12+CC12) -> 0 | CE12: =MAX(0,MIN(BV12,CB12+CC12-CD12)) -> 0 | CF12: =BV12-CE12 -> 0 | CG12: =CB12+CC12-CD12-CE12 -> 0 | CH12: =CK11 -> 0 | CI12: =CH12*$CB$5/12 -> 0 | CJ12: =MIN($CB$6,CH12+CI12) -> 0 | CK12: =CH12+CI12-CJ12 -> 0
A13: 5 | B13: ='1 Your debts'!$B$16-(L13+V13+AF13+AP13+AZ13+BJ13+BT13+CD13) -> 200 | C13: =O13+Y13+AI13+AS13+BC13+BM13+BW13+CG13 -> 23096.229 | D13: =K13+U13+AE13+AO13+AY13+BI13+BS13+CC13 -> 196.44839 | F13: =S13+AC13+AM13+AW13+BG13+BQ13+CA13+CK13 -> 24138.756 | G13: =Q13+AA13+AK13+AU13+BE13+BO13+BY13+CI13 -> 213.63607 | J13: =O12 -> 3302.2997 | K13: =J13*$J$5/12 -> 68.770391 | L13: =MIN($J$6,J13+K13) -> 105 | M13: =MAX(0,MIN($B13,J13+K13-L13)) -> 200 | N13: =$B13-M13 -> 0 | O13: =J13+K13-L13-M13 -> 3066.0701 | P13: =S12 -> 4127.6384 | Q13: =P13*$J$5/12 -> 85.95807 | R13: =MIN($J$6,P13+Q13) -> 105 | S13: =P13+Q13-R13 -> 4108.5965 | T13: =Y12 -> 1738.4225 | U13: =T13*$T$5/12 -> 28.959222 | V13: =MIN($T$6,T13+U13) -> 45 | W13: =MAX(0,MIN(N13,T13+U13-V13)) -> 0 | X13: =N13-W13 -> 0 | Y13: =T13+U13-V13-W13 -> 1722.3817 | Z13: =AC12 -> 1738.4225 | AA13: =Z13*$T$5/12 -> 28.959222 | AB13: =MIN($T$6,Z13+AA13) -> 45 | AC13: =Z13+AA13-AB13 -> 1722.3817 | AD13: =AI12 -> 6851.1274 | AE13: =AD13*$AD$5/12 -> 45.103256 | AF13: =MIN($AD$6,AD13+AE13) -> 210 | AG13: =MAX(0,MIN(X13,AD13+AE13-AF13)) -> 0 | AH13: =X13-AG13 -> 0 | AI13: =AD13+AE13-AF13-AG13 -> 6686.2307 | AJ13: =AM12 -> 6851.1274 | AK13: =AJ13*$AD$5/12 -> 45.103256 | AL13: =MIN($AD$6,AJ13+AK13) -> 210 | AM13: =AJ13+AK13-AL13 -> 6686.2307 | AN13: =AS12 -> 11697.931 | AO13: =AN13*$AN$5/12 -> 53.615518 | AP13: =MIN($AN$6,AN13+AO13) -> 130 | AQ13: =MAX(0,MIN(AH13,AN13+AO13-AP13)) -> 0 | AR13: =AH13-AQ13 -> 0 | AS13: =AN13+AO13-AP13-AQ13 -> 11621.547 | AT13: =AW12 -> 11697.931 | AU13: =AT13*$AN$5/12 -> 53.615518 | AV13: =MIN($AN$6,AT13+AU13) -> 130 | AW13: =AT13+AU13-AV13 -> 11621.547 | AX13: =BC12 -> 0 | AY13: =AX13*$AX$5/12 -> 0 | AZ13: =MIN($AX$6,AX13+AY13) -> 0 | BA13: =MAX(0,MIN(AR13,AX13+AY13-AZ13)) -> 0 | BB13: =AR13-BA13 -> 0 | BC13: =AX13+AY13-AZ13-BA13 -> 0 | BD13: =BG12 -> 0 | BE13: =BD13*$AX$5/12 -> 0 | BF13: =MIN($AX$6,BD13+BE13) -> 0 | BG13: =BD13+BE13-BF13 -> 0 | BH13: =BM12 -> 0 | BI13: =BH13*$BH$5/12 -> 0 | BJ13: =MIN($BH$6,BH13+BI13) -> 0 | BK13: =MAX(0,MIN(BB13,BH13+BI13-BJ13)) -> 0 | BL13: =BB13-BK13 -> 0 | BM13: =BH13+BI13-BJ13-BK13 -> 0 | BN13: =BQ12 -> 0 | BO13: =BN13*$BH$5/12 -> 0 | BP13: =MIN($BH$6,BN13+BO13) -> 0 | BQ13: =BN13+BO13-BP13 -> 0 | BR13: =BW12 -> 0 | BS13: =BR13*$BR$5/12 -> 0 | BT13: =MIN($BR$6,BR13+BS13) -> 0 | BU13: =MAX(0,MIN(BL13,BR13+BS13-BT13)) -> 0 | BV13: =BL13-BU13 -> 0 | BW13: =BR13+BS13-BT13-BU13 -> 0 | BX13: =CA12 -> 0 | BY13: =BX13*$BR$5/12 -> 0 | BZ13: =MIN($BR$6,BX13+BY13) -> 0 | CA13: =BX13+BY13-BZ13 -> 0 | CB13: =CG12 -> 0 | CC13: =CB13*$CB$5/12 -> 0 | CD13: =MIN($CB$6,CB13+CC13) -> 0 | CE13: =MAX(0,MIN(BV13,CB13+CC13-CD13)) -> 0 | CF13: =BV13-CE13 -> 0 | CG13: =CB13+CC13-CD13-CE13 -> 0 | CH13: =CK12 -> 0 | CI13: =CH13*$CB$5/12 -> 0 | CJ13: =MIN($CB$6,CH13+CI13) -> 0 | CK13: =CH13+CI13-CJ13 -> 0
A14: 6 | B14: ='1 Your debts'!$B$16-(L14+V14+AF14+AP14+AZ14+BJ14+BT14+CD14) -> 200 | C14: =O14+Y14+AI14+AS14+BC14+BM14+BW14+CG14 -> 22596.055 | D14: =K14+U14+AE14+AO14+AY14+BI14+BS14+CC14 -> 189.82603 | F14: =S14+AC14+AM14+AW14+BG14+BQ14+CA14+CK14 -> 23860.292 | G14: =Q14+AA14+AK14+AU14+BE14+BO14+BY14+CI14 -> 211.53664 | J14: =O13 -> 3066.0701 | K14: =J14*$J$5/12 -> 63.850909 | L14: =MIN($J$6,J14+K14) -> 105 | M14: =MAX(0,MIN($B14,J14+K14-L14)) -> 200 | N14: =$B14-M14 -> 0 | O14: =J14+K14-L14-M14 -> 2824.921 | P14: =S13 -> 4108.5965 | Q14: =P14*$J$5/12 -> 85.561522 | R14: =MIN($J$6,P14+Q14) -> 105 | S14: =P14+Q14-R14 -> 4089.158 | T14: =Y13 -> 1722.3817 | U14: =T14*$T$5/12 -> 28.692009 | V14: =MIN($T$6,T14+U14) -> 45 | W14: =MAX(0,MIN(N14,T14+U14-V14)) -> 0 | X14: =N14-W14 -> 0 | Y14: =T14+U14-V14-W14 -> 1706.0737 | Z14: =AC13 -> 1722.3817 | AA14: =Z14*$T$5/12 -> 28.692009 | AB14: =MIN($T$6,Z14+AA14) -> 45 | AC14: =Z14+AA14-AB14 -> 1706.0737 | AD14: =AI13 -> 6686.2307 | AE14: =AD14*$AD$5/12 -> 44.017685 | AF14: =MIN($AD$6,AD14+AE14) -> 210 | AG14: =MAX(0,MIN(X14,AD14+AE14-AF14)) -> 0 | AH14: =X14-AG14 -> 0 | AI14: =AD14+AE14-AF14-AG14 -> 6520.2484 | AJ14: =AM13 -> 6686.2307 | AK14: =AJ14*$AD$5/12 -> 44.017685 | AL14: =MIN($AD$6,AJ14+AK14) -> 210 | AM14: =AJ14+AK14-AL14 -> 6520.2484 | AN14: =AS13 -> 11621.547 | AO14: =AN14*$AN$5/12 -> 53.265422 | AP14: =MIN($AN$6,AN14+AO14) -> 130 | AQ14: =MAX(0,MIN(AH14,AN14+AO14-AP14)) -> 0 | AR14: =AH14-AQ14 -> 0 | AS14: =AN14+AO14-AP14-AQ14 -> 11544.812 | AT14: =AW13 -> 11621.547 | AU14: =AT14*$AN$5/12 -> 53.265422 | AV14: =MIN($AN$6,AT14+AU14) -> 130 | AW14: =AT14+AU14-AV14 -> 11544.812 | AX14: =BC13 -> 0 | AY14: =AX14*$AX$5/12 -> 0 | AZ14: =MIN($AX$6,AX14+AY14) -> 0 | BA14: =MAX(0,MIN(AR14,AX14+AY14-AZ14)) -> 0 | BB14: =AR14-BA14 -> 0 | BC14: =AX14+AY14-AZ14-BA14 -> 0 | BD14: =BG13 -> 0 | BE14: =BD14*$AX$5/12 -> 0 | BF14: =MIN($AX$6,BD14+BE14) -> 0 | BG14: =BD14+BE14-BF14 -> 0 | BH14: =BM13 -> 0 | BI14: =BH14*$BH$5/12 -> 0 | BJ14: =MIN($BH$6,BH14+BI14) -> 0 | BK14: =MAX(0,MIN(BB14,BH14+BI14-BJ14)) -> 0 | BL14: =BB14-BK14 -> 0 | BM14: =BH14+BI14-BJ14-BK14 -> 0 | BN14: =BQ13 -> 0 | BO14: =BN14*$BH$5/12 -> 0 | BP14: =MIN($BH$6,BN14+BO14) -> 0 | BQ14: =BN14+BO14-BP14 -> 0 | BR14: =BW13 -> 0 | BS14: =BR14*$BR$5/12 -> 0 | BT14: =MIN($BR$6,BR14+BS14) -> 0 | BU14: =MAX(0,MIN(BL14,BR14+BS14-BT14)) -> 0 | BV14: =BL14-BU14 -> 0 | BW14: =BR14+BS14-BT14-BU14 -> 0 | BX14: =CA13 -> 0 | BY14: =BX14*$BR$5/12 -> 0 | BZ14: =MIN($BR$6,BX14+BY14) -> 0 | CA14: =BX14+BY14-BZ14 -> 0 | CB14: =CG13 -> 0 | CC14: =CB14*$CB$5/12 -> 0 | CD14: =MIN($CB$6,CB14+CC14) -> 0 | CE14: =MAX(0,MIN(BV14,CB14+CC14-CD14)) -> 0 | CF14: =BV14-CE14 -> 0 | CG14: =CB14+CC14-CD14-CE14 -> 0 | CH14: =CK13 -> 0 | CI14: =CH14*$CB$5/12 -> 0 | CJ14: =MIN($CB$6,CH14+CI14) -> 0 | CK14: =CH14+CI14-CJ14 -> 0
A15: 7 | B15: ='1 Your debts'!$B$16-(L15+V15+AF15+AP15+AZ15+BJ15+BT15+CD15) -> 200 | C15: =O15+Y15+AI15+AS15+BC15+BM15+BW15+CG15 -> 22089.143 | D15: =K15+U15+AE15+AO15+AY15+BI15+BS15+CC15 -> 183.08802 | F15: =S15+AC15+AM15+AW15+BG15+BQ15+CA15+CK15 -> 23579.708 | G15: =Q15+AA15+AK15+AU15+BE15+BO15+BY15+CI15 -> 209.41575 | J15: =O14 -> 2824.921 | K15: =J15*$J$5/12 -> 58.828979 | L15: =MIN($J$6,J15+K15) -> 105 | M15: =MAX(0,MIN($B15,J15+K15-L15)) -> 200 | N15: =$B15-M15 -> 0 | O15: =J15+K15-L15-M15 -> 2578.75 | P15: =S14 -> 4089.158 | Q15: =P15*$J$5/12 -> 85.156716 | R15: =MIN($J$6,P15+Q15) -> 105 | S15: =P15+Q15-R15 -> 4069.3147 | T15: =Y14 -> 1706.0737 | U15: =T15*$T$5/12 -> 28.420345 | V15: =MIN($T$6,T15+U15) -> 45 | W15: =MAX(0,MIN(N15,T15+U15-V15)) -> 0 | X15: =N15-W15 -> 0 | Y15: =T15+U15-V15-W15 -> 1689.4941 | Z15: =AC14 -> 1706.0737 | AA15: =Z15*$T$5/12 -> 28.420345 | AB15: =MIN($T$6,Z15+AA15) -> 45 | AC15: =Z15+AA15-AB15 -> 1689.4941 | AD15: =AI14 -> 6520.2484 | AE15: =AD15*$AD$5/12 -> 42.924968 | AF15: =MIN($AD$6,AD15+AE15) -> 210 | AG15: =MAX(0,MIN(X15,AD15+AE15-AF15)) -> 0 | AH15: =X15-AG15 -> 0 | AI15: =AD15+AE15-AF15-AG15 -> 6353.1733 | AJ15: =AM14 -> 6520.2484 | AK15: =AJ15*$AD$5/12 -> 42.924968 | AL15: =MIN($AD$6,AJ15+AK15) -> 210 | AM15: =AJ15+AK15-AL15 -> 6353.1733 | AN15: =AS14 -> 11544.812 | AO15: =AN15*$AN$5/12 -> 52.913722 | AP15: =MIN($AN$6,AN15+AO15) -> 130 | AQ15: =MAX(0,MIN(AH15,AN15+AO15-AP15)) -> 0 | AR15: =AH15-AQ15 -> 0 | AS15: =AN15+AO15-AP15-AQ15 -> 11467.726 | AT15: =AW14 -> 11544.812 | AU15: =AT15*$AN$5/12 -> 52.913722 | AV15: =MIN($AN$6,AT15+AU15) -> 130 | AW15: =AT15+AU15-AV15 -> 11467.726 | AX15: =BC14 -> 0 | AY15: =AX15*$AX$5/12 -> 0 | AZ15: =MIN($AX$6,AX15+AY15) -> 0 | BA15: =MAX(0,MIN(AR15,AX15+AY15-AZ15)) -> 0 | BB15: =AR15-BA15 -> 0 | BC15: =AX15+AY15-AZ15-BA15 -> 0 | BD15: =BG14 -> 0 | BE15: =BD15*$AX$5/12 -> 0 | BF15: =MIN($AX$6,BD15+BE15) -> 0 | BG15: =BD15+BE15-BF15 -> 0 | BH15: =BM14 -> 0 | BI15: =BH15*$BH$5/12 -> 0 | BJ15: =MIN($BH$6,BH15+BI15) -> 0 | BK15: =MAX(0,MIN(BB15,BH15+BI15-BJ15)) -> 0 | BL15: =BB15-BK15 -> 0 | BM15: =BH15+BI15-BJ15-BK15 -> 0 | BN15: =BQ14 -> 0 | BO15: =BN15*$BH$5/12 -> 0 | BP15: =MIN($BH$6,BN15+BO15) -> 0 | BQ15: =BN15+BO15-BP15 -> 0 | BR15: =BW14 -> 0 | BS15: =BR15*$BR$5/12 -> 0 | BT15: =MIN($BR$6,BR15+BS15) -> 0 | BU15: =MAX(0,MIN(BL15,BR15+BS15-BT15)) -> 0 | BV15: =BL15-BU15 -> 0 | BW15: =BR15+BS15-BT15-BU15 -> 0 | BX15: =CA14 -> 0 | BY15: =BX15*$BR$5/12 -> 0 | BZ15: =MIN($BR$6,BX15+BY15) -> 0 | CA15: =BX15+BY15-BZ15 -> 0 | CB15: =CG14 -> 0 | CC15: =CB15*$CB$5/12 -> 0 | CD15: =MIN($CB$6,CB15+CC15) -> 0 | CE15: =MAX(0,MIN(BV15,CB15+CC15-CD15)) -> 0 | CF15: =BV15-CE15 -> 0 | CG15: =CB15+CC15-CD15-CE15 -> 0 | CH15: =CK14 -> 0 | CI15: =CH15*$CB$5/12 -> 0 | CJ15: =MIN($CB$6,CH15+CI15) -> 0 | CK15: =CH15+CI15-CJ15 -> 0
A16: 8 | B16: ='1 Your debts'!$B$16-(L16+V16+AF16+AP16+AZ16+BJ16+BT16+CD16) -> 200 | C16: =O16+Y16+AI16+AS16+BC16+BM16+BW16+CG16 -> 21575.375 | D16: =K16+U16+AE16+AO16+AY16+BI16+BS16+CC16 -> 176.23209 | F16: =S16+AC16+AM16+AW16+BG16+BQ16+CA16+CK16 -> 23296.981 | G16: =Q16+AA16+AK16+AU16+BE16+BO16+BY16+CI16 -> 207.2731 | J16: =O15 -> 2578.75 | K16: =J16*$J$5/12 -> 53.702468 | L16: =MIN($J$6,J16+K16) -> 105 | M16: =MAX(0,MIN($B16,J16+K16-L16)) -> 200 | N16: =$B16-M16 -> 0 | O16: =J16+K16-L16-M16 -> 2327.4524 | P16: =S15 -> 4069.3147 | Q16: =P16*$J$5/12 -> 84.743479 | R16: =MIN($J$6,P16+Q16) -> 105 | S16: =P16+Q16-R16 -> 4049.0582 | T16: =Y15 -> 1689.4941 | U16: =T16*$T$5/12 -> 28.144156 | V16: =MIN($T$6,T16+U16) -> 45 | W16: =MAX(0,MIN(N16,T16+U16-V16)) -> 0 | X16: =N16-W16 -> 0 | Y16: =T16+U16-V16-W16 -> 1672.6382 | Z16: =AC15 -> 1689.4941 | AA16: =Z16*$T$5/12 -> 28.144156 | AB16: =MIN($T$6,Z16+AA16) -> 45 | AC16: =Z16+AA16-AB16 -> 1672.6382 | AD16: =AI15 -> 6353.1733 | AE16: =AD16*$AD$5/12 -> 41.825058 | AF16: =MIN($AD$6,AD16+AE16) -> 210 | AG16: =MAX(0,MIN(X16,AD16+AE16-AF16)) -> 0 | AH16: =X16-AG16 -> 0 | AI16: =AD16+AE16-AF16-AG16 -> 6184.9984 | AJ16: =AM15 -> 6353.1733 | AK16: =AJ16*$AD$5/12 -> 41.825058 | AL16: =MIN($AD$6,AJ16+AK16) -> 210 | AM16: =AJ16+AK16-AL16 -> 6184.9984 | AN16: =AS15 -> 11467.726 | AO16: =AN16*$AN$5/12 -> 52.56041 | AP16: =MIN($AN$6,AN16+AO16) -> 130 | AQ16: =MAX(0,MIN(AH16,AN16+AO16-AP16)) -> 0 | AR16: =AH16-AQ16 -> 0 | AS16: =AN16+AO16-AP16-AQ16 -> 11390.286 | AT16: =AW15 -> 11467.726 | AU16: =AT16*$AN$5/12 -> 52.56041 | AV16: =MIN($AN$6,AT16+AU16) -> 130 | AW16: =AT16+AU16-AV16 -> 11390.286 | AX16: =BC15 -> 0 | AY16: =AX16*$AX$5/12 -> 0 | AZ16: =MIN($AX$6,AX16+AY16) -> 0 | BA16: =MAX(0,MIN(AR16,AX16+AY16-AZ16)) -> 0 | BB16: =AR16-BA16 -> 0 | BC16: =AX16+AY16-AZ16-BA16 -> 0 | BD16: =BG15 -> 0 | BE16: =BD16*$AX$5/12 -> 0 | BF16: =MIN($AX$6,BD16+BE16) -> 0 | BG16: =BD16+BE16-BF16 -> 0 | BH16: =BM15 -> 0 | BI16: =BH16*$BH$5/12 -> 0 | BJ16: =MIN($BH$6,BH16+BI16) -> 0 | BK16: =MAX(0,MIN(BB16,BH16+BI16-BJ16)) -> 0 | BL16: =BB16-BK16 -> 0 | BM16: =BH16+BI16-BJ16-BK16 -> 0 | BN16: =BQ15 -> 0 | BO16: =BN16*$BH$5/12 -> 0 | BP16: =MIN($BH$6,BN16+BO16) -> 0 | BQ16: =BN16+BO16-BP16 -> 0 | BR16: =BW15 -> 0 | BS16: =BR16*$BR$5/12 -> 0 | BT16: =MIN($BR$6,BR16+BS16) -> 0 | BU16: =MAX(0,MIN(BL16,BR16+BS16-BT16)) -> 0 | BV16: =BL16-BU16 -> 0 | BW16: =BR16+BS16-BT16-BU16 -> 0 | BX16: =CA15 -> 0 | BY16: =BX16*$BR$5/12 -> 0 | BZ16: =MIN($BR$6,BX16+BY16) -> 0 | CA16: =BX16+BY16-BZ16 -> 0 | CB16: =CG15 -> 0 | CC16: =CB16*$CB$5/12 -> 0 | CD16: =MIN($CB$6,CB16+CC16) -> 0 | CE16: =MAX(0,MIN(BV16,CB16+CC16-CD16)) -> 0 | CF16: =BV16-CE16 -> 0 | CG16: =CB16+CC16-CD16-CE16 -> 0 | CH16: =CK15 -> 0 | CI16: =CH16*$CB$5/12 -> 0 | CJ16: =MIN($CB$6,CH16+CI16) -> 0 | CK16: =CH16+CI16-CJ16 -> 0
A17: 9 | B17: ='1 Your debts'!$B$16-(L17+V17+AF17+AP17+AZ17+BJ17+BT17+CD17) -> 200 | C17: =O17+Y17+AI17+AS17+BC17+BM17+BW17+CG17 -> 21054.631 | D17: =K17+U17+AE17+AO17+AY17+BI17+BS17+CC17 -> 169.25595 | F17: =S17+AC17+AM17+AW17+BG17+BQ17+CA17+CK17 -> 23012.089 | G17: =Q17+AA17+AK17+AU17+BE17+BO17+BY17+CI17 -> 205.10839 | J17: =O16 -> 2327.4524 | K17: =J17*$J$5/12 -> 48.469197 | L17: =MIN($J$6,J17+K17) -> 105 | M17: =MAX(0,MIN($B17,J17+K17-L17)) -> 200 | N17: =$B17-M17 -> 0 | O17: =J17+K17-L17-M17 -> 2070.9216 | P17: =S16 -> 4049.0582 | Q17: =P17*$J$5/12 -> 84.321637 | R17: =MIN($J$6,P17+Q17) -> 105 | S17: =P17+Q17-R17 -> 4028.3798 | T17: =Y16 -> 1672.6382 | U17: =T17*$T$5/12 -> 27.863365 | V17: =MIN($T$6,T17+U17) -> 45 | W17: =MAX(0,MIN(N17,T17+U17-V17)) -> 0 | X17: =N17-W17 -> 0 | Y17: =T17+U17-V17-W17 -> 1655.5016 | Z17: =AC16 -> 1672.6382 | AA17: =Z17*$T$5/12 -> 27.863365 | AB17: =MIN($T$6,Z17+AA17) -> 45 | AC17: =Z17+AA17-AB17 -> 1655.5016 | AD17: =AI16 -> 6184.9984 | AE17: =AD17*$AD$5/12 -> 40.717906 | AF17: =MIN($AD$6,AD17+AE17) -> 210 | AG17: =MAX(0,MIN(X17,AD17+AE17-AF17)) -> 0 | AH17: =X17-AG17 -> 0 | AI17: =AD17+AE17-AF17-AG17 -> 6015.7163 | AJ17: =AM16 -> 6184.9984 | AK17: =AJ17*$AD$5/12 -> 40.717906 | AL17: =MIN($AD$6,AJ17+AK17) -> 210 | AM17: =AJ17+AK17-AL17 -> 6015.7163 | AN17: =AS16 -> 11390.286 | AO17: =AN17*$AN$5/12 -> 52.205479 | AP17: =MIN($AN$6,AN17+AO17) -> 130 | AQ17: =MAX(0,MIN(AH17,AN17+AO17-AP17)) -> 0 | AR17: =AH17-AQ17 -> 0 | AS17: =AN17+AO17-AP17-AQ17 -> 11312.492 | AT17: =AW16 -> 11390.286 | AU17: =AT17*$AN$5/12 -> 52.205479 | AV17: =MIN($AN$6,AT17+AU17) -> 130 | AW17: =AT17+AU17-AV17 -> 11312.492 | AX17: =BC16 -> 0 | AY17: =AX17*$AX$5/12 -> 0 | AZ17: =MIN($AX$6,AX17+AY17) -> 0 | BA17: =MAX(0,MIN(AR17,AX17+AY17-AZ17)) -> 0 | BB17: =AR17-BA17 -> 0 | BC17: =AX17+AY17-AZ17-BA17 -> 0 | BD17: =BG16 -> 0 | BE17: =BD17*$AX$5/12 -> 0 | BF17: =MIN($AX$6,BD17+BE17) -> 0 | BG17: =BD17+BE17-BF17 -> 0 | BH17: =BM16 -> 0 | BI17: =BH17*$BH$5/12 -> 0 | BJ17: =MIN($BH$6,BH17+BI17) -> 0 | BK17: =MAX(0,MIN(BB17,BH17+BI17-BJ17)) -> 0 | BL17: =BB17-BK17 -> 0 | BM17: =BH17+BI17-BJ17-BK17 -> 0 | BN17: =BQ16 -> 0 | BO17: =BN17*$BH$5/12 -> 0 | BP17: =MIN($BH$6,BN17+BO17) -> 0 | BQ17: =BN17+BO17-BP17 -> 0 | BR17: =BW16 -> 0 | BS17: =BR17*$BR$5/12 -> 0 | BT17: =MIN($BR$6,BR17+BS17) -> 0 | BU17: =MAX(0,MIN(BL17,BR17+BS17-BT17)) -> 0 | BV17: =BL17-BU17 -> 0 | BW17: =BR17+BS17-BT17-BU17 -> 0 | BX17: =CA16 -> 0 | BY17: =BX17*$BR$5/12 -> 0 | BZ17: =MIN($BR$6,BX17+BY17) -> 0 | CA17: =BX17+BY17-BZ17 -> 0 | CB17: =CG16 -> 0 | CC17: =CB17*$CB$5/12 -> 0 | CD17: =MIN($CB$6,CB17+CC17) -> 0 | CE17: =MAX(0,MIN(BV17,CB17+CC17-CD17)) -> 0 | CF17: =BV17-CE17 -> 0 | CG17: =CB17+CC17-CD17-CE17 -> 0 | CH17: =CK16 -> 0 | CI17: =CH17*$CB$5/12 -> 0 | CJ17: =MIN($CB$6,CH17+CI17) -> 0 | CK17: =CH17+CI17-CJ17 -> 0
A18: 10 | B18: ='1 Your debts'!$B$16-(L18+V18+AF18+AP18+AZ18+BJ18+BT18+CD18) -> 200 | C18: =O18+Y18+AI18+AS18+BC18+BM18+BW18+CG18 -> 20526.788 | D18: =K18+U18+AE18+AO18+AY18+BI18+BS18+CC18 -> 162.15723 | F18: =S18+AC18+AM18+AW18+BG18+BQ18+CA18+CK18 -> 22725.011 | G18: =Q18+AA18+AK18+AU18+BE18+BO18+BY18+CI18 -> 202.92129 | J18: =O17 -> 2070.9216 | K18: =J18*$J$5/12 -> 43.126943 | L18: =MIN($J$6,J18+K18) -> 105 | M18: =MAX(0,MIN($B18,J18+K18-L18)) -> 200 | N18: =$B18-M18 -> 0 | O18: =J18+K18-L18-M18 -> 1809.0486 | P18: =S17 -> 4028.3798 | Q18: =P18*$J$5/12 -> 83.89101 | R18: =MIN($J$6,P18+Q18) -> 105 | S18: =P18+Q18-R18 -> 4007.2709 | T18: =Y17 -> 1655.5016 | U18: =T18*$T$5/12 -> 27.577898 | V18: =MIN($T$6,T18+U18) -> 45 | W18: =MAX(0,MIN(N18,T18+U18-V18)) -> 0 | X18: =N18-W18 -> 0 | Y18: =T18+U18-V18-W18 -> 1638.0795 | Z18: =AC17 -> 1655.5016 | AA18: =Z18*$T$5/12 -> 27.577898 | AB18: =MIN($T$6,Z18+AA18) -> 45 | AC18: =Z18+AA18-AB18 -> 1638.0795 | AD18: =AI17 -> 6015.7163 | AE18: =AD18*$AD$5/12 -> 39.603466 | AF18: =MIN($AD$6,AD18+AE18) -> 210 | AG18: =MAX(0,MIN(X18,AD18+AE18-AF18)) -> 0 | AH18: =X18-AG18 -> 0 | AI18: =AD18+AE18-AF18-AG18 -> 5845.3198 | AJ18: =AM17 -> 6015.7163 | AK18: =AJ18*$AD$5/12 -> 39.603466 | AL18: =MIN($AD$6,AJ18+AK18) -> 210 | AM18: =AJ18+AK18-AL18 -> 5845.3198 | AN18: =AS17 -> 11312.492 | AO18: =AN18*$AN$5/12 -> 51.84892 | AP18: =MIN($AN$6,AN18+AO18) -> 130 | AQ18: =MAX(0,MIN(AH18,AN18+AO18-AP18)) -> 0 | AR18: =AH18-AQ18 -> 0 | AS18: =AN18+AO18-AP18-AQ18 -> 11234.341 | AT18: =AW17 -> 11312.492 | AU18: =AT18*$AN$5/12 -> 51.84892 | AV18: =MIN($AN$6,AT18+AU18) -> 130 | AW18: =AT18+AU18-AV18 -> 11234.341 | AX18: =BC17 -> 0 | AY18: =AX18*$AX$5/12 -> 0 | AZ18: =MIN($AX$6,AX18+AY18) -> 0 | BA18: =MAX(0,MIN(AR18,AX18+AY18-AZ18)) -> 0 | BB18: =AR18-BA18 -> 0 | BC18: =AX18+AY18-AZ18-BA18 -> 0 | BD18: =BG17 -> 0 | BE18: =BD18*$AX$5/12 -> 0 | BF18: =MIN($AX$6,BD18+BE18) -> 0 | BG18: =BD18+BE18-BF18 -> 0 | BH18: =BM17 -> 0 | BI18: =BH18*$BH$5/12 -> 0 | BJ18: =MIN($BH$6,BH18+BI18) -> 0 | BK18: =MAX(0,MIN(BB18,BH18+BI18-BJ18)) -> 0 | BL18: =BB18-BK18 -> 0 | BM18: =BH18+BI18-BJ18-BK18 -> 0 | BN18: =BQ17 -> 0 | BO18: =BN18*$BH$5/12 -> 0 | BP18: =MIN($BH$6,BN18+BO18) -> 0 | BQ18: =BN18+BO18-BP18 -> 0 | BR18: =BW17 -> 0 | BS18: =BR18*$BR$5/12 -> 0 | BT18: =MIN($BR$6,BR18+BS18) -> 0 | BU18: =MAX(0,MIN(BL18,BR18+BS18-BT18)) -> 0 | BV18: =BL18-BU18 -> 0 | BW18: =BR18+BS18-BT18-BU18 -> 0 | BX18: =CA17 -> 0 | BY18: =BX18*$BR$5/12 -> 0 | BZ18: =MIN($BR$6,BX18+BY18) -> 0 | CA18: =BX18+BY18-BZ18 -> 0 | CB18: =CG17 -> 0 | CC18: =CB18*$CB$5/12 -> 0 | CD18: =MIN($CB$6,CB18+CC18) -> 0 | CE18: =MAX(0,MIN(BV18,CB18+CC18-CD18)) -> 0 | CF18: =BV18-CE18 -> 0 | CG18: =CB18+CC18-CD18-CE18 -> 0 | CH18: =CK17 -> 0 | CI18: =CH18*$CB$5/12 -> 0 | CJ18: =MIN($CB$6,CH18+CI18) -> 0 | CK18: =CH18+CI18-CJ18 -> 0
A19: 11 | B19: ='1 Your debts'!$B$16-(L19+V19+AF19+AP19+AZ19+BJ19+BT19+CD19) -> 200 | C19: =O19+Y19+AI19+AS19+BC19+BM19+BW19+CG19 -> 19991.722 | D19: =K19+U19+AE19+AO19+AY19+BI19+BS19+CC19 -> 154.93353 | F19: =S19+AC19+AM19+AW19+BG19+BQ19+CA19+CK19 -> 22435.722 | G19: =Q19+AA19+AK19+AU19+BE19+BO19+BY19+CI19 -> 200.71151 | J19: =O18 -> 1809.0486 | K19: =J19*$J$5/12 -> 37.673436 | L19: =MIN($J$6,J19+K19) -> 105 | M19: =MAX(0,MIN($B19,J19+K19-L19)) -> 200 | N19: =$B19-M19 -> 0 | O19: =J19+K19-L19-M19 -> 1541.722 | P19: =S18 -> 4007.2709 | Q19: =P19*$J$5/12 -> 83.451416 | R19: =MIN($J$6,P19+Q19) -> 105 | S19: =P19+Q19-R19 -> 3985.7223 | T19: =Y18 -> 1638.0795 | U19: =T19*$T$5/12 -> 27.287674 | V19: =MIN($T$6,T19+U19) -> 45 | W19: =MAX(0,MIN(N19,T19+U19-V19)) -> 0 | X19: =N19-W19 -> 0 | Y19: =T19+U19-V19-W19 -> 1620.3672 | Z19: =AC18 -> 1638.0795 | AA19: =Z19*$T$5/12 -> 27.287674 | AB19: =MIN($T$6,Z19+AA19) -> 45 | AC19: =Z19+AA19-AB19 -> 1620.3672 | AD19: =AI18 -> 5845.3198 | AE19: =AD19*$AD$5/12 -> 38.481688 | AF19: =MIN($AD$6,AD19+AE19) -> 210 | AG19: =MAX(0,MIN(X19,AD19+AE19-AF19)) -> 0 | AH19: =X19-AG19 -> 0 | AI19: =AD19+AE19-AF19-AG19 -> 5673.8014 | AJ19: =AM18 -> 5845.3198 | AK19: =AJ19*$AD$5/12 -> 38.481688 | AL19: =MIN($AD$6,AJ19+AK19) -> 210 | AM19: =AJ19+AK19-AL19 -> 5673.8014 | AN19: =AS18 -> 11234.341 | AO19: =AN19*$AN$5/12 -> 51.490728 | AP19: =MIN($AN$6,AN19+AO19) -> 130 | AQ19: =MAX(0,MIN(AH19,AN19+AO19-AP19)) -> 0 | AR19: =AH19-AQ19 -> 0 | AS19: =AN19+AO19-AP19-AQ19 -> 11155.831 | AT19: =AW18 -> 11234.341 | AU19: =AT19*$AN$5/12 -> 51.490728 | AV19: =MIN($AN$6,AT19+AU19) -> 130 | AW19: =AT19+AU19-AV19 -> 11155.831 | AX19: =BC18 -> 0 | AY19: =AX19*$AX$5/12 -> 0 | AZ19: =MIN($AX$6,AX19+AY19) -> 0 | BA19: =MAX(0,MIN(AR19,AX19+AY19-AZ19)) -> 0 | BB19: =AR19-BA19 -> 0 | BC19: =AX19+AY19-AZ19-BA19 -> 0 | BD19: =BG18 -> 0 | BE19: =BD19*$AX$5/12 -> 0 | BF19: =MIN($AX$6,BD19+BE19) -> 0 | BG19: =BD19+BE19-BF19 -> 0 | BH19: =BM18 -> 0 | BI19: =BH19*$BH$5/12 -> 0 | BJ19: =MIN($BH$6,BH19+BI19) -> 0 | BK19: =MAX(0,MIN(BB19,BH19+BI19-BJ19)) -> 0 | BL19: =BB19-BK19 -> 0 | BM19: =BH19+BI19-BJ19-BK19 -> 0 | BN19: =BQ18 -> 0 | BO19: =BN19*$BH$5/12 -> 0 | BP19: =MIN($BH$6,BN19+BO19) -> 0 | BQ19: =BN19+BO19-BP19 -> 0 | BR19: =BW18 -> 0 | BS19: =BR19*$BR$5/12 -> 0 | BT19: =MIN($BR$6,BR19+BS19) -> 0 | BU19: =MAX(0,MIN(BL19,BR19+BS19-BT19)) -> 0 | BV19: =BL19-BU19 -> 0 | BW19: =BR19+BS19-BT19-BU19 -> 0 | BX19: =CA18 -> 0 | BY19: =BX19*$BR$5/12 -> 0 | BZ19: =MIN($BR$6,BX19+BY19) -> 0 | CA19: =BX19+BY19-BZ19 -> 0 | CB19: =CG18 -> 0 | CC19: =CB19*$CB$5/12 -> 0 | CD19: =MIN($CB$6,CB19+CC19) -> 0 | CE19: =MAX(0,MIN(BV19,CB19+CC19-CD19)) -> 0 | CF19: =BV19-CE19 -> 0 | CG19: =CB19+CC19-CD19-CE19 -> 0 | CH19: =CK18 -> 0 | CI19: =CH19*$CB$5/12 -> 0 | CJ19: =MIN($CB$6,CH19+CI19) -> 0 | CK19: =CH19+CI19-CJ19 -> 0
A20: 12 | B20: ='1 Your debts'!$B$16-(L20+V20+AF20+AP20+AZ20+BJ20+BT20+CD20) -> 200 | C20: =O20+Y20+AI20+AS20+BC20+BM20+BW20+CG20 -> 19449.304 | D20: =K20+U20+AE20+AO20+AY20+BI20+BS20+CC20 -> 147.5824 | F20: =S20+AC20+AM20+AW20+BG20+BQ20+CA20+CK20 -> 22144.201 | G20: =Q20+AA20+AK20+AU20+BE20+BO20+BY20+CI20 -> 198.4787 | J20: =O19 -> 1541.722 | K20: =J20*$J$5/12 -> 32.106361 | L20: =MIN($J$6,J20+K20) -> 105 | M20: =MAX(0,MIN($B20,J20+K20-L20)) -> 200 | N20: =$B20-M20 -> 0 | O20: =J20+K20-L20-M20 -> 1268.8284 | P20: =S19 -> 3985.7223 | Q20: =P20*$J$5/12 -> 83.002666 | R20: =MIN($J$6,P20+Q20) -> 105 | S20: =P20+Q20-R20 -> 3963.7249 | T20: =Y19 -> 1620.3672 | U20: =T20*$T$5/12 -> 26.992617 | V20: =MIN($T$6,T20+U20) -> 45 | W20: =MAX(0,MIN(N20,T20+U20-V20)) -> 0 | X20: =N20-W20 -> 0 | Y20: =T20+U20-V20-W20 -> 1602.3598 | Z20: =AC19 -> 1620.3672 | AA20: =Z20*$T$5/12 -> 26.992617 | AB20: =MIN($T$6,Z20+AA20) -> 45 | AC20: =Z20+AA20-AB20 -> 1602.3598 | AD20: =AI19 -> 5673.8014 | AE20: =AD20*$AD$5/12 -> 37.352526 | AF20: =MIN($AD$6,AD20+AE20) -> 210 | AG20: =MAX(0,MIN(X20,AD20+AE20-AF20)) -> 0 | AH20: =X20-AG20 -> 0 | AI20: =AD20+AE20-AF20-AG20 -> 5501.154 | AJ20: =AM19 -> 5673.8014 | AK20: =AJ20*$AD$5/12 -> 37.352526 | AL20: =MIN($AD$6,AJ20+AK20) -> 210 | AM20: =AJ20+AK20-AL20 -> 5501.154 | AN20: =AS19 -> 11155.831 | AO20: =AN20*$AN$5/12 -> 51.130894 | AP20: =MIN($AN$6,AN20+AO20) -> 130 | AQ20: =MAX(0,MIN(AH20,AN20+AO20-AP20)) -> 0 | AR20: =AH20-AQ20 -> 0 | AS20: =AN20+AO20-AP20-AQ20 -> 11076.962 | AT20: =AW19 -> 11155.831 | AU20: =AT20*$AN$5/12 -> 51.130894 | AV20: =MIN($AN$6,AT20+AU20) -> 130 | AW20: =AT20+AU20-AV20 -> 11076.962 | AX20: =BC19 -> 0 | AY20: =AX20*$AX$5/12 -> 0 | AZ20: =MIN($AX$6,AX20+AY20) -> 0 | BA20: =MAX(0,MIN(AR20,AX20+AY20-AZ20)) -> 0 | BB20: =AR20-BA20 -> 0 | BC20: =AX20+AY20-AZ20-BA20 -> 0 | BD20: =BG19 -> 0 | BE20: =BD20*$AX$5/12 -> 0 | BF20: =MIN($AX$6,BD20+BE20) -> 0 | BG20: =BD20+BE20-BF20 -> 0 | BH20: =BM19 -> 0 | BI20: =BH20*$BH$5/12 -> 0 | BJ20: =MIN($BH$6,BH20+BI20) -> 0 | BK20: =MAX(0,MIN(BB20,BH20+BI20-BJ20)) -> 0 | BL20: =BB20-BK20 -> 0 | BM20: =BH20+BI20-BJ20-BK20 -> 0 | BN20: =BQ19 -> 0 | BO20: =BN20*$BH$5/12 -> 0 | BP20: =MIN($BH$6,BN20+BO20) -> 0 | BQ20: =BN20+BO20-BP20 -> 0 | BR20: =BW19 -> 0 | BS20: =BR20*$BR$5/12 -> 0 | BT20: =MIN($BR$6,BR20+BS20) -> 0 | BU20: =MAX(0,MIN(BL20,BR20+BS20-BT20)) -> 0 | BV20: =BL20-BU20 -> 0 | BW20: =BR20+BS20-BT20-BU20 -> 0 | BX20: =CA19 -> 0 | BY20: =BX20*$BR$5/12 -> 0 | BZ20: =MIN($BR$6,BX20+BY20) -> 0 | CA20: =BX20+BY20-BZ20 -> 0 | CB20: =CG19 -> 0 | CC20: =CB20*$CB$5/12 -> 0 | CD20: =MIN($CB$6,CB20+CC20) -> 0 | CE20: =MAX(0,MIN(BV20,CB20+CC20-CD20)) -> 0 | CF20: =BV20-CE20 -> 0 | CG20: =CB20+CC20-CD20-CE20 -> 0 | CH20: =CK19 -> 0 | CI20: =CH20*$CB$5/12 -> 0 | CJ20: =MIN($CB$6,CH20+CI20) -> 0 | CK20: =CH20+CI20-CJ20 -> 0
A21: 13 | B21: ='1 Your debts'!$B$16-(L21+V21+AF21+AP21+AZ21+BJ21+BT21+CD21) -> 200 | C21: =O21+Y21+AI21+AS21+BC21+BM21+BW21+CG21 -> 18899.406 | D21: =K21+U21+AE21+AO21+AY21+BI21+BS21+CC21 -> 140.10134 | F21: =S21+AC21+AM21+AW21+BG21+BQ21+CA21+CK21 -> 21850.424 | G21: =Q21+AA21+AK21+AU21+BE21+BO21+BY21+CI21 -> 196.22256 | J21: =O20 -> 1268.8284 | K21: =J21*$J$5/12 -> 26.423351 | L21: =MIN($J$6,J21+K21) -> 105 | M21: =MAX(0,MIN($B21,J21+K21-L21)) -> 200 | N21: =$B21-M21 -> 0 | O21: =J21+K21-L21-M21 -> 990.25171 | P21: =S20 -> 3963.7249 | Q21: =P21*$J$5/12 -> 82.544572 | R21: =MIN($J$6,P21+Q21) -> 105 | S21: =P21+Q21-R21 -> 3941.2695 | T21: =Y20 -> 1602.3598 | U21: =T21*$T$5/12 -> 26.692644 | V21: =MIN($T$6,T21+U21) -> 45 | W21: =MAX(0,MIN(N21,T21+U21-V21)) -> 0 | X21: =N21-W21 -> 0 | Y21: =T21+U21-V21-W21 -> 1584.0524 | Z21: =AC20 -> 1602.3598 | AA21: =Z21*$T$5/12 -> 26.692644 | AB21: =MIN($T$6,Z21+AA21) -> 45 | AC21: =Z21+AA21-AB21 -> 1584.0524 | AD21: =AI20 -> 5501.154 | AE21: =AD21*$AD$5/12 -> 36.21593 | AF21: =MIN($AD$6,AD21+AE21) -> 210 | AG21: =MAX(0,MIN(X21,AD21+AE21-AF21)) -> 0 | AH21: =X21-AG21 -> 0 | AI21: =AD21+AE21-AF21-AG21 -> 5327.3699 | AJ21: =AM20 -> 5501.154 | AK21: =AJ21*$AD$5/12 -> 36.21593 | AL21: =MIN($AD$6,AJ21+AK21) -> 210 | AM21: =AJ21+AK21-AL21 -> 5327.3699 | AN21: =AS20 -> 11076.962 | AO21: =AN21*$AN$5/12 -> 50.76941 | AP21: =MIN($AN$6,AN21+AO21) -> 130 | AQ21: =MAX(0,MIN(AH21,AN21+AO21-AP21)) -> 0 | AR21: =AH21-AQ21 -> 0 | AS21: =AN21+AO21-AP21-AQ21 -> 10997.732 | AT21: =AW20 -> 11076.962 | AU21: =AT21*$AN$5/12 -> 50.76941 | AV21: =MIN($AN$6,AT21+AU21) -> 130 | AW21: =AT21+AU21-AV21 -> 10997.732 | AX21: =BC20 -> 0 | AY21: =AX21*$AX$5/12 -> 0 | AZ21: =MIN($AX$6,AX21+AY21) -> 0 | BA21: =MAX(0,MIN(AR21,AX21+AY21-AZ21)) -> 0 | BB21: =AR21-BA21 -> 0 | BC21: =AX21+AY21-AZ21-BA21 -> 0 | BD21: =BG20 -> 0 | BE21: =BD21*$AX$5/12 -> 0 | BF21: =MIN($AX$6,BD21+BE21) -> 0 | BG21: =BD21+BE21-BF21 -> 0 | BH21: =BM20 -> 0 | BI21: =BH21*$BH$5/12 -> 0 | BJ21: =MIN($BH$6,BH21+BI21) -> 0 | BK21: =MAX(0,MIN(BB21,BH21+BI21-BJ21)) -> 0 | BL21: =BB21-BK21 -> 0 | BM21: =BH21+BI21-BJ21-BK21 -> 0 | BN21: =BQ20 -> 0 | BO21: =BN21*$BH$5/12 -> 0 | BP21: =MIN($BH$6,BN21+BO21) -> 0 | BQ21: =BN21+BO21-BP21 -> 0 | BR21: =BW20 -> 0 | BS21: =BR21*$BR$5/12 -> 0 | BT21: =MIN($BR$6,BR21+BS21) -> 0 | BU21: =MAX(0,MIN(BL21,BR21+BS21-BT21)) -> 0 | BV21: =BL21-BU21 -> 0 | BW21: =BR21+BS21-BT21-BU21 -> 0 | BX21: =CA20 -> 0 | BY21: =BX21*$BR$5/12 -> 0 | BZ21: =MIN($BR$6,BX21+BY21) -> 0 | CA21: =BX21+BY21-BZ21 -> 0 | CB21: =CG20 -> 0 | CC21: =CB21*$CB$5/12 -> 0 | CD21: =MIN($CB$6,CB21+CC21) -> 0 | CE21: =MAX(0,MIN(BV21,CB21+CC21-CD21)) -> 0 | CF21: =BV21-CE21 -> 0 | CG21: =CB21+CC21-CD21-CE21 -> 0 | CH21: =CK20 -> 0 | CI21: =CH21*$CB$5/12 -> 0 | CJ21: =MIN($CB$6,CH21+CI21) -> 0 | CK21: =CH21+CI21-CJ21 -> 0
... A248: 240 | B248: ='1 Your debts'!$B$16-(L248+V248+AF248+AP248+AZ248+BJ248+BT248+CD248) -> 690 | C248: =O248+Y248+AI248+AS248+BC248+BM248+BW248+CG248 -> 0 | D248: =K248+U248+AE248+AO248+AY248+BI248+BS248+CC248 -> 0 | F248: =S248+AC248+AM248+AW248+BG248+BQ248+CA248+CK248 -> 0 | G248: =Q248+AA248+AK248+AU248+BE248+BO248+BY248+CI248 -> 0 | J248: =O247 -> 0 | K248: =J248*$J$5/12 -> 0 | L248: =MIN($J$6,J248+K248) -> 0 | M248: =MAX(0,MIN($B248,J248+K248-L248)) -> 0 | N248: =$B248-M248 -> 690 | O248: =J248+K248-L248-M248 -> 0 | P248: =S247 -> 0 | Q248: =P248*$J$5/12 -> 0 | R248: =MIN($J$6,P248+Q248) -> 0 | S248: =P248+Q248-R248 -> 0 | T248: =Y247 -> 0 | U248: =T248*$T$5/12 -> 0 | V248: =MIN($T$6,T248+U248) -> 0 | W248: =MAX(0,MIN(N248,T248+U248-V248)) -> 0 | X248: =N248-W248 -> 690 | Y248: =T248+U248-V248-W248 -> 0 | Z248: =AC247 -> 0 | AA248: =Z248*$T$5/12 -> 0 | AB248: =MIN($T$6,Z248+AA248) -> 0 | AC248: =Z248+AA248-AB248 -> 0 | AD248: =AI247 -> 0 | AE248: =AD248*$AD$5/12 -> 0 | AF248: =MIN($AD$6,AD248+AE248) -> 0 | AG248: =MAX(0,MIN(X248,AD248+AE248-AF248)) -> 0 | AH248: =X248-AG248 -> 690 | AI248: =AD248+AE248-AF248-AG248 -> 0 | AJ248: =AM247 -> 0 | AK248: =AJ248*$AD$5/12 -> 0 | AL248: =MIN($AD$6,AJ248+AK248) -> 0 | AM248: =AJ248+AK248-AL248 -> 0 | AN248: =AS247 -> 0 | AO248: =AN248*$AN$5/12 -> 0 | AP248: =MIN($AN$6,AN248+AO248) -> 0 | AQ248: =MAX(0,MIN(AH248,AN248+AO248-AP248)) -> 0 | AR248: =AH248-AQ248 -> 690 | AS248: =AN248+AO248-AP248-AQ248 -> 0 | AT248: =AW247 -> 0 | AU248: =AT248*$AN$5/12 -> 0 | AV248: =MIN($AN$6,AT248+AU248) -> 0 | AW248: =AT248+AU248-AV248 -> 0 | AX248: =BC247 -> 0 | AY248: =AX248*$AX$5/12 -> 0 | AZ248: =MIN($AX$6,AX248+AY248) -> 0 | BA248: =MAX(0,MIN(AR248,AX248+AY248-AZ248)) -> 0 | BB248: =AR248-BA248 -> 690 | BC248: =AX248+AY248-AZ248-BA248 -> 0 | BD248: =BG247 -> 0 | BE248: =BD248*$AX$5/12 -> 0 | BF248: =MIN($AX$6,BD248+BE248) -> 0 | BG248: =BD248+BE248-BF248 -> 0 | BH248: =BM247 -> 0 | BI248: =BH248*$BH$5/12 -> 0 | BJ248: =MIN($BH$6,BH248+BI248) -> 0 | BK248: =MAX(0,MIN(BB248,BH248+BI248-BJ248)) -> 0 | BL248: =BB248-BK248 -> 690 | BM248: =BH248+BI248-BJ248-BK248 -> 0 | BN248: =BQ247 -> 0 | BO248: =BN248*$BH$5/12 -> 0 | BP248: =MIN($BH$6,BN248+BO248) -> 0 | BQ248: =BN248+BO248-BP248 -> 0 | BR248: =BW247 -> 0 | BS248: =BR248*$BR$5/12 -> 0 | BT248: =MIN($BR$6,BR248+BS248) -> 0 | BU248: =MAX(0,MIN(BL248,BR248+BS248-BT248)) -> 0 | BV248: =BL248-BU248 -> 690 | BW248: =BR248+BS248-BT248-BU248 -> 0 | BX248: =CA247 -> 0 | BY248: =BX248*$BR$5/12 -> 0 | BZ248: =MIN($BR$6,BX248+BY248) -> 0 | CA248: =BX248+BY248-BZ248 -> 0 | CB248: =CG247 -> 0 | CC248: =CB248*$CB$5/12 -> 0 | CD248: =MIN($CB$6,CB248+CC248) -> 0 | CE248: =MAX(0,MIN(BV248,CB248+CC248-CD248)) -> 0 | CF248: =BV248-CE248 -> 690 | CG248: =CB248+CC248-CD248-CE248 -> 0 | CH248: =CK247 -> 0 | CI248: =CH248*$CB$5/12 -> 0 | CJ248: =MIN($CB$6,CH248+CI248) -> 0 | CK248: =CH248+CI248-CJ248 -> 0
