Workbook

Sheet Start here
A1: Rat Race Escape Planner
A2: Know your freedom number. Track every income stream. Execute for 100 days.
A4: 1. Open '1 Your numbers' and replace the blue cells with your own. Gray cells are formulas: leave them alone.
A5: 2. Read your freedom number and your years to freedom. Then change one input at a time and watch what moves.
A6: 3. List every income stream in '2 Income streams'. The goal is passive and asset income, not more hours.
A7: 4. Run '3 Rule of 100' with your real offer, then log every week in '5 Weekly log'. Execution beats education.
A8: 5. '4 Projection' shows the whole road, year by year, in today's dollars.
A10: Colors
A11: Blue = you type here
A12: Gray = formula
A14: How the math works
A15: Freedom number = yearly spending / safe withdrawal rate (the 4% rule is a rule of thumb, not a guarantee).
... A21: License: personal use for you and your household. Please do not resell or redistribute the file.

Sheet 1 Your numbers
A1: 1 Your numbers
A2: Replace the blue cells. Example numbers shown.
A3: Input | B3: Value | C3: Note
A4: Your age | B4: 35
A5: Monthly spending you need (today's dollars) | B5: 3000 | C5: What 'enough' costs you each month
A6: Monthly take-home income | B6: 4500
A7: Invested today | B7: 15000 | C7: Savings and investments you could live off
A8: Amount you invest each month | B8: 900
A9: Expected yearly return (assumption) | B9: 0.07 | C9: Not a promise; try 4%, 7%, 10%
A10: Expected yearly inflation (assumption) | B10: 0.03
A11: Safe yearly withdrawal rate | B11: 0.04 | C11: 4% is a common rule of thumb
A12: Extra you could invest each month | B12: 100 | C12: For the 'what if' line below
A15: Your results | B15: Value | C15: What it means
A16: Freedom number | B16: =$B$5*12/$B$11 -> 900000 | C16: The invested amount that covers your spending for good
A17: Real yearly return | B17: =(1+$B$9)/(1+$B$10)-1 -> 0.038834951 | C17: Return after inflation: keeps everything in today's dollars
A18: Savings rate | B18: =IFERROR($B$8/$B$6,0) -> 0.2 | C18: Share of take-home income you invest
A19: Months to freedom | B19: =IF($B$7>=B16,0,IFERROR(NPER(B17/12,-$B$8,-$B$7,B16),"never at these numbers")) -> 430.55882
A20: Years to freedom | B20: =IF(ISNUMBER(B19),B19/12,"never at these numbers") -> 35.879902
A21: Your freedom age | B21: =IF(ISNUMBER(B20),$B$4+B20,"-") -> 70.879902
A22: Passive income your money makes today | B22: =$B$7*$B$11/12 -> 50 | C22: Per month, at your withdrawal rate
A23: Share of your spending already covered | B23: =IFERROR(B22/$B$5,0) -> 0.016666667
A24: Years to freedom with the extra monthly amount | B24: =IF($B$7>=B16,0,IFERROR(NPER(B17/12,-($B$8+$B$12),-$B$7,B16)/12,"never at these numbers")) -> 33.962575
A25: Years the extra amount saves you | B25: =IF(AND(ISNUMBER(B20),ISNUMBER(B24)),B20-B24,"-") -> 1.9173268 | C25: Small, boring, automatic. That is the whole trick.

Sheet 2 Income streams
A1: 2 Income streams
A2: Active trades hours for money. Passive runs without you. Asset is something you own that pays.
A3: Stream | B3: Type | C3: Per month | D3: Hours per week | E3: $ per hour | F3: What it is
A4: Day job (example: replace) | B4: Active | C4: 4500 | D4: 40 | E4: =IF(C4="","",IF(N(D4)>0,C4/(D4*4.33),"no hours")) -> 25.981524 | F4: =IF(B4="Active","Trades your time",IF(B4="Passive","Runs without you",IF(B4="Asset","You own it",""))) -> Trades your time
A5: Side project (example) | B5: Active | C5: 300 | D5: 5 | E5: =IF(C5="","",IF(N(D5)>0,C5/(D5*4.33),"no hours")) -> 13.856813 | F5: =IF(B5="Active","Trades your time",IF(B5="Passive","Runs without you",IF(B5="Asset","You own it",""))) -> Trades your time
A6: Index fund dividends (example) | B6: Asset | C6: 40 | D6: 0 | E6: =IF(C6="","",IF(N(D6)>0,C6/(D6*4.33),"no hours")) -> no hours | F6: =IF(B6="Active","Trades your time",IF(B6="Passive","Runs without you",IF(B6="Asset","You own it",""))) -> You own it
A7: Digital product sales (example) | B7: Passive | C7: 0 | D7: 0 | E7: =IF(C7="","",IF(N(D7)>0,C7/(D7*4.33),"no hours")) -> no hours | F7: =IF(B7="Active","Trades your time",IF(B7="Passive","Runs without you",IF(B7="Asset","You own it",""))) -> Runs without you
E8: =IF(C8="","",IF(N(D8)>0,C8/(D8*4.33),"no hours")) | F8: =IF(B8="Active","Trades your time",IF(B8="Passive","Runs without you",IF(B8="Asset","You own it","")))
E9: =IF(C9="","",IF(N(D9)>0,C9/(D9*4.33),"no hours")) | F9: =IF(B9="Active","Trades your time",IF(B9="Passive","Runs without you",IF(B9="Asset","You own it","")))
E10: =IF(C10="","",IF(N(D10)>0,C10/(D10*4.33),"no hours")) | F10: =IF(B10="Active","Trades your time",IF(B10="Passive","Runs without you",IF(B10="Asset","You own it","")))
E11: =IF(C11="","",IF(N(D11)>0,C11/(D11*4.33),"no hours")) | F11: =IF(B11="Active","Trades your time",IF(B11="Passive","Runs without you",IF(B11="Asset","You own it","")))
E12: =IF(C12="","",IF(N(D12)>0,C12/(D12*4.33),"no hours")) | F12: =IF(B12="Active","Trades your time",IF(B12="Passive","Runs without you",IF(B12="Asset","You own it","")))
E13: =IF(C13="","",IF(N(D13)>0,C13/(D13*4.33),"no hours")) | F13: =IF(B13="Active","Trades your time",IF(B13="Passive","Runs without you",IF(B13="Asset","You own it","")))
E14: =IF(C14="","",IF(N(D14)>0,C14/(D14*4.33),"no hours")) | F14: =IF(B14="Active","Trades your time",IF(B14="Passive","Runs without you",IF(B14="Asset","You own it","")))
E15: =IF(C15="","",IF(N(D15)>0,C15/(D15*4.33),"no hours")) | F15: =IF(B15="Active","Trades your time",IF(B15="Passive","Runs without you",IF(B15="Asset","You own it","")))
A17: Total per month | C17: =SUM(C4:C15) -> 4840
A18: Passive + asset income per month | C18: =SUMIF(B4:B15,"Passive",C4:C15)+SUMIF(B4:B15,"Asset",C4:C15) -> 40
A19: Passive + asset share of your spending | C19: =IFERROR(C18/'1 Your numbers'!B5,0) -> 0.013333333
A20: Hours you trade each week | C20: =SUMIF(B4:B15,"Active",D4:D15) -> 45
A22: The escape is the day C19 reaches 100%: your spending is paid by money that works while you do not.

Sheet 3 Rule of 100
A1: 3 Rule of 100
A2: Volume beats talent. 100 outreaches a day for 100 days is 10,000 shots at a customer.
A4: Outreaches per day | B4: 100
A5: Days | B5: 100
A6: Yes-rate (a guess until you test it) | B6: 0.01
A7: Average sale per customer | B7: 150
A9: Total outreaches | B9: =B4*B5 -> 10000
A10: Customers | B10: =B9*B6 -> 100
A11: Revenue | B11: =B10*B7 -> 15000
A13: If your yes-rate is | B13: Customers | C13: Revenue
A14: 0.002 | B14: =$B$9*A14 -> 20 | C14: =B14*$B$7 -> 3000
A15: 0.005 | B15: =$B$9*A15 -> 50 | C15: =B15*$B$7 -> 7500
A16: 0.01 | B16: =$B$9*A16 -> 100 | C16: =B16*$B$7 -> 15000
A17: 0.02 | B17: =$B$9*A17 -> 200 | C17: =B17*$B$7 -> 30000
A18: 0.03 | B18: =$B$9*A18 -> 300 | C18: =B18*$B$7 -> 45000
A20: Hypothetical. Your real yes-rate and sale size are unknown until you make the calls: log them in '5 Weekly log' and replace the guesses.

Sheet 4 Projection
A1: 4 Projection
A2: Year by year, in today's dollars, from your numbers. Highlighted when your money covers your spending.
A3: Year | B3: Age | C3: Invested | D3: Passive income / month | E3: Spending covered | F3: Freedom number
A4: 0 | B4: ='1 Your numbers'!$B$4+A4 -> 35 | C4: =FV('1 Your numbers'!$B$17/12,A4*12,-'1 Your numbers'!$B$8,-'1 Your numbers'!$B$7) -> 15000 | D4: =C4*'1 Your numbers'!$B$11/12 -> 50 | E4: =IFERROR(D4/'1 Your numbers'!$B$5,0) -> 0.016666667 | F4: ='1 Your numbers'!$B$16 -> 900000
A5: 1 | B5: ='1 Your numbers'!$B$4+A5 -> 36 | C5: =FV('1 Your numbers'!$B$17/12,A5*12,-'1 Your numbers'!$B$8,-'1 Your numbers'!$B$7) -> 26587.327 | D5: =C5*'1 Your numbers'!$B$11/12 -> 88.624425 | E5: =IFERROR(D5/'1 Your numbers'!$B$5,0) -> 0.029541475 | F5: ='1 Your numbers'!$B$16 -> 900000
A6: 2 | B6: ='1 Your numbers'!$B$4+A6 -> 37 | C6: =FV('1 Your numbers'!$B$17/12,A6*12,-'1 Your numbers'!$B$8,-'1 Your numbers'!$B$7) -> 38632.745 | D6: =C6*'1 Your numbers'!$B$11/12 -> 128.77582 | E6: =IFERROR(D6/'1 Your numbers'!$B$5,0) -> 0.042925272 | F6: ='1 Your numbers'!$B$16 -> 900000
A7: 3 | B7: ='1 Your numbers'!$B$4+A7 -> 38 | C7: =FV('1 Your numbers'!$B$17/12,A7*12,-'1 Your numbers'!$B$8,-'1 Your numbers'!$B$7) -> 51154.362 | D7: =C7*'1 Your numbers'!$B$11/12 -> 170.51454 | E7: =IFERROR(D7/'1 Your numbers'!$B$5,0) -> 0.05683818 | F7: ='1 Your numbers'!$B$16 -> 900000
A8: 4 | B8: ='1 Your numbers'!$B$4+A8 -> 39 | C8: =FV('1 Your numbers'!$B$17/12,A8*12,-'1 Your numbers'!$B$8,-'1 Your numbers'!$B$7) -> 64171.005 | D8: =C8*'1 Your numbers'!$B$11/12 -> 213.90335 | E8: =IFERROR(D8/'1 Your numbers'!$B$5,0) -> 0.071301117 | F8: ='1 Your numbers'!$B$16 -> 900000
A9: 5 | B9: ='1 Your numbers'!$B$4+A9 -> 40 | C9: =FV('1 Your numbers'!$B$17/12,A9*12,-'1 Your numbers'!$B$8,-'1 Your numbers'!$B$7) -> 77702.244 | D9: =C9*'1 Your numbers'!$B$11/12 -> 259.00748 | E9: =IFERROR(D9/'1 Your numbers'!$B$5,0) -> 0.086335827 | F9: ='1 Your numbers'!$B$16 -> 900000
A10: 6 | B10: ='1 Your numbers'!$B$4+A10 -> 41 | C10: =FV('1 Your numbers'!$B$17/12,A10*12,-'1 Your numbers'!$B$8,-'1 Your numbers'!$B$7) -> 91768.423 | D10: =C10*'1 Your numbers'!$B$11/12 -> 305.89474 | E10: =IFERROR(D10/'1 Your numbers'!$B$5,0) -> 0.10196491 | F10: ='1 Your numbers'!$B$16 -> 900000
A11: 7 | B11: ='1 Your numbers'!$B$4+A11 -> 42 | C11: =FV('1 Your numbers'!$B$17/12,A11*12,-'1 Your numbers'!$B$8,-'1 Your numbers'!$B$7) -> 106390.69 | D11: =C11*'1 Your numbers'!$B$11/12 -> 354.63563 | E11: =IFERROR(D11/'1 Your numbers'!$B$5,0) -> 0.11821188 | F11: ='1 Your numbers'!$B$16 -> 900000
A12: 8 | B12: ='1 Your numbers'!$B$4+A12 -> 43 | C12: =FV('1 Your numbers'!$B$17/12,A12*12,-'1 Your numbers'!$B$8,-'1 Your numbers'!$B$7) -> 121591.03 | D12: =C12*'1 Your numbers'!$B$11/12 -> 405.30343 | E12: =IFERROR(D12/'1 Your numbers'!$B$5,0) -> 0.13510114 | F12: ='1 Your numbers'!$B$16 -> 900000
A13: 9 | B13: ='1 Your numbers'!$B$4+A13 -> 44 | C13: =FV('1 Your numbers'!$B$17/12,A13*12,-'1 Your numbers'!$B$8,-'1 Your numbers'!$B$7) -> 137392.3 | D13: =C13*'1 Your numbers'!$B$11/12 -> 457.97432 | E13: =IFERROR(D13/'1 Your numbers'!$B$5,0) -> 0.15265811 | F13: ='1 Your numbers'!$B$16 -> 900000
A14: 10 | B14: ='1 Your numbers'!$B$4+A14 -> 45 | C14: =FV('1 Your numbers'!$B$17/12,A14*12,-'1 Your numbers'!$B$8,-'1 Your numbers'!$B$7) -> 153818.24 | D14: =C14*'1 Your numbers'!$B$11/12 -> 512.72748 | E14: =IFERROR(D14/'1 Your numbers'!$B$5,0) -> 0.17090916 | F14: ='1 Your numbers'!$B$16 -> 900000
A15: 11 | B15: ='1 Your numbers'!$B$4+A15 -> 46 | C15: =FV('1 Your numbers'!$B$17/12,A15*12,-'1 Your numbers'!$B$8,-'1 Your numbers'!$B$7) -> 170893.57 | D15: =C15*'1 Your numbers'!$B$11/12 -> 569.64523 | E15: =IFERROR(D15/'1 Your numbers'!$B$5,0) -> 0.18988174 | F15: ='1 Your numbers'!$B$16 -> 900000
... A44: 40 | B44: ='1 Your numbers'!$B$4+A44 -> 75 | C44: =FV('1 Your numbers'!$B$17/12,A44*12,-'1 Your numbers'!$B$8,-'1 Your numbers'!$B$7) -> 1104061.3 | D44: =C44*'1 Your numbers'!$B$11/12 -> 3680.2044 | E44: =IFERROR(D44/'1 Your numbers'!$B$5,0) -> 1.2267348 | F44: ='1 Your numbers'!$B$16 -> 900000

Sheet 5 Weekly log
A1: 5 Weekly log
A2: Thirteen weeks is about 100 days. Fill in what happened, not what you hoped for.
A3: Week | B3: Outreaches | C3: Replies | D3: Sales | E3: Revenue | F3: Hours worked | G3: What I learned
A4: 1
A5: 2
A6: 3
A7: 4
A8: 5
A9: 6
A10: 7
A11: 8
A12: 9
A13: 10
A14: 11
A15: 12
A16: 13
A18: Totals | B18: =SUM(B4:B16) -> 0 | C18: =SUM(C4:C16) -> 0 | D18: =SUM(D4:D16) -> 0 | E18: =SUM(E4:E16) -> 0 | F18: =SUM(F4:F16) -> 0
A20: Reply rate | B20: =IFERROR(C18/B18,0) -> 0
A21: Close rate (sales per reply) | B21: =IFERROR(D18/C18,0) -> 0
A22: Yes-rate (sales per outreach) | B22: =IFERROR(D18/B18,0) -> 0
A23: Revenue per hour | B23: =IFERROR(E18/F18,0) -> 0
A24: Copy your real yes-rate into '3 Rule of 100' and watch the forecast become honest.
